Workbook

Sheet README
A1: Pauseiro & Vance Legal Group — Multi-Office Consolidation Model
B4: What this is
B5: A synthetic 3-office professional-services group (P&V Miami [Group HQ], P&V Chicago, P&V Dallas) with 18 months of GL, bank statement and budget data (Jan 2024 - Jun 2025), built as a portfolio piece for accounting / audit / controlling / FP&A roles.
B7: How the tabs fit together
B8: PQ_* tabs - raw data as Power Query would land it after combining the 3 offices' source exports (see power_query_steps.md for the M code). Nothing upstream of these tabs is manual.
B9: Close_Checklist - the month-end close task list for the open period (Jun 2025), so the workbook reads like an active close, not just a finished model.
B10: Trial_Balance - net movement by account, by entity and combined, for the open month. Every number is a live SUMIFS against PQ_GL_Data.
B11: Bank_Reconciliation - book-to-bank tie-out per entity: book balance + unrecorded bank items = adjusted book balance; bank balance + outstanding items = adjusted bank balance. The two adjusted figures agree, which is the point of a bank rec.
B12: Consolidation - Group P&L: each office's numbers, the combined total, and the intercompany elimination for the HQ shared-services billing, with a note on why operating income doesn't move even though revenue and expense both shrink.
B13: Budget_vs_Actual - variance by entity/account for the open month, flagged and ranked.
B14: Dashboard - KPI tiles and trend charts for the Group.
B16: What it's built to demonstrate
B17: Accounting / audit / controlling / FP&A: a full close cycle (accruals, reconciliations, variance review, period lock) across a multi-entity structure.
... B21: Data modeling - grain, keys, fact & dimension tables: schema.sql, with the grain and keys of every fact table documented inline.

Sheet Dashboard
A1: Pauseiro & Vance Legal Group — Executive Dashboard — 2025-06
A3: Group Revenue (Net) | C3: Group Operating Income | E3: Group Operating Margin | G3: Open Bank Reconciling Items | I3: Largest Budget Overspend
A4: =Consolidation!E25 -> 241003.08 | C4: =Consolidation!E28 -> 60162.38 | E4: =Consolidation!E28/Consolidation!E25 -> 0.24963324 | G4: =COUNTIFS(PQ_Bank_Data!$H:$H,"2025-06",PQ_Bank_Data!$F:$F,"Unmatched - Book Adjustment Needed")+SUMPRODUCT(--(Bank_Reconciliation!$B$9:$D$9<>0)) -> 9 | I4: =INDEX(Budget_vs_Actual!$E:$E,MATCH(1,Budget_vs_Actual!$G:$G,0)) -> 1648.7

Sheet Close_Checklist
A1: Month-End Close Checklist — 2025-06 (Group)
A3: # | B3: Close Task | C3: Entity Scope | D3: Owner | E3: Due (business day) | F3: Status
A4: 1 | B4: Post final billing & cash receipts | C4: All entities | D4: Office Bookkeeper | E4: BD+2 | F4: Complete
A5: 2 | B5: Reverse prior-month payroll accrual | C5: All entities | D5: Controller | E5: BD+1 | F5: Complete
A6: 3 | B6: Run payroll & book current accrual | C6: All entities | D6: Controller | E6: BD+3 | F6: Complete
A7: 4 | B7: Amortize prepaid insurance | C7: All entities | D7: Controller | E7: BD+3 | F7: Complete
A8: 5 | B8: Book monthly depreciation | C8: All entities | D8: Controller | E8: BD+3 | F8: Complete
A9: 6 | B9: Bill intercompany shared services (HQ to branches) | C9: MIA -> CHI, DAL | D9: Controller | E9: BD+4 | F9: Complete
A10: 7 | B10: Settle prior-month intercompany balances | C10: CHI, DAL -> MIA | D10: Controller | E10: BD+5 | F10: Complete
A11: 8 | B11: Complete bank reconciliation, all accounts | C11: All entities | D11: Controller | E11: BD+5 | F11: In Progress
A12: 9 | B12: Book bank-identified items not yet in GL (fees, interest) | C12: All entities | D12: Controller | E12: BD+5 | F12: Not Started
A13: 10 | B13: Reconcile intercompany AR/AP between entities | C13: MIA, CHI, DAL | D13: Group Controller | E13: BD+6 | F13: Not Started
A14: 11 | B14: Prepare consolidation elimination entries | C14: Group | D14: Group Controller | E14: BD+6 | F14: Not Started
A15: 12 | B15: Review budget-vs-actual variances >10% | C15: All entities | D15: FP&A | E15: BD+7 | F15: Blocked
... A18: 15 | B18: Distribute close package | C18: Group | D18: Group Controller | E18: BD+9 | F18: Not Started
B20: Note: "Blocked" - budget-vs-actual review is waiting on the shared-services allocation reconciliation (task 10) to close first.

Sheet Trial_Balance
A1: Trial Balance — Net Movement by Account — 2025-06
A3: Account Code | B3: Account Name | C3: Account Type | D3: MIA | E3: CHI | F3: DAL | G3: Combined
A4: 1000 | B4: Cash - Operating | C4: Asset | D4: =SUMIFS(PQ_GL_Data!$I:$I,PQ_GL_Data!$C:$C,"MIA",PQ_GL_Data!$E:$E,"1000",PQ_GL_Data!$N:$N,"2025-06")-SUMIFS(PQ_GL_Data!$J:$J,PQ_GL_Data!$C:$C,"MIA",PQ_GL_Data!$E:$E,"1000",PQ_GL_Data!$N:$N,"2025-06") -> 33024.53 | E4: =SUMIFS(PQ_GL_Data!$I:$I,PQ_GL_Data!$C:$C,"CHI",PQ_GL_Data!$E:$E,"1000",PQ_GL_Data!$N:$N,"2025-06")-SUMIFS(PQ_GL_Data!$J:$J,PQ_GL_Data!$C:$C,"CHI",PQ_GL_Data!$E:$E,"1000",PQ_GL_Data!$N:$N,"2025-06") -> 10400.85 | F4: =SUMIFS(PQ_GL_Data!$I:$I,PQ_GL_Data!$C:$C,"DAL",PQ_GL_Data!$E:$E,"1000",PQ_GL_Data!$N:$N,"2025-06")-SUMIFS(PQ_GL_Data!$J:$J,PQ_GL_Data!$C:$C,"DAL",PQ_GL_Data!$E:$E,"1000",PQ_GL_Data!$N:$N,"2025-06") -> 7680.73 | G4: =SUM(D4:F4) -> 51106.11
A5: 1100 | B5: Accounts Receivable | C5: Asset | D5: =SUMIFS(PQ_GL_Data!$I:$I,PQ_GL_Data!$C:$C,"MIA",PQ_GL_Data!$E:$E,"1100",PQ_GL_Data!$N:$N,"2025-06")-SUMIFS(PQ_GL_Data!$J:$J,PQ_GL_Data!$C:$C,"MIA",PQ_GL_Data!$E:$E,"1100",PQ_GL_Data!$N:$N,"2025-06") -> 6868.81 | E5: =SUMIFS(PQ_GL_Data!$I:$I,PQ_GL_Data!$C:$C,"CHI",PQ_GL_Data!$E:$E,"1100",PQ_GL_Data!$N:$N,"2025-06")-SUMIFS(PQ_GL_Data!$J:$J,PQ_GL_Data!$C:$C,"CHI",PQ_GL_Data!$E:$E,"1100",PQ_GL_Data!$N:$N,"2025-06") -> 5680.75 | F5: =SUMIFS(PQ_GL_Data!$I:$I,PQ_GL_Data!$C:$C,"DAL",PQ_GL_Data!$E:$E,"1100",PQ_GL_Data!$N:$N,"2025-06")-SUMIFS(PQ_GL_Data!$J:$J,PQ_GL_Data!$C:$C,"DAL",PQ_GL_Data!$E:$E,"1100",PQ_GL_Data!$N:$N,"2025-06") -> 2407.11 | G5: =SUM(D5:F5) -> 14956.67
A6: 1200 | B6: Prepaid Expenses | C6: Asset | D6: =SUMIFS(PQ_GL_Data!$I:$I,PQ_GL_Data!$C:$C,"MIA",PQ_GL_Data!$E:$E,"1200",PQ_GL_Data!$N:$N,"2025-06")-SUMIFS(PQ_GL_Data!$J:$J,PQ_GL_Data!$C:$C,"MIA",PQ_GL_Data!$E:$E,"1200",PQ_GL_Data!$N:$N,"2025-06") -> -1450 | E6: =SUMIFS(PQ_GL_Data!$I:$I,PQ_GL_Data!$C:$C,"CHI",PQ_GL_Data!$E:$E,"1200",PQ_GL_Data!$N:$N,"2025-06")-SUMIFS(PQ_GL_Data!$J:$J,PQ_GL_Data!$C:$C,"CHI",PQ_GL_Data!$E:$E,"1200",PQ_GL_Data!$N:$N,"2025-06") -> -899 | F6: =SUMIFS(PQ_GL_Data!$I:$I,PQ_GL_Data!$C:$C,"DAL",PQ_GL_Data!$E:$E,"1200",PQ_GL_Data!$N:$N,"2025-06")-SUMIFS(PQ_GL_Data!$J:$J,PQ_GL_Data!$C:$C,"DAL",PQ_GL_Data!$E:$E,"1200",PQ_GL_Data!$N:$N,"2025-06") -> -797.5 | G6: =SUM(D6:F6) -> -3146.5
A7: 1300 | B7: Intercompany Receivable | C7: Asset | D7: =SUMIFS(PQ_GL_Data!$I:$I,PQ_GL_Data!$C:$C,"MIA",PQ_GL_Data!$E:$E,"1300",PQ_GL_Data!$N:$N,"2025-06")-SUMIFS(PQ_GL_Data!$J:$J,PQ_GL_Data!$C:$C,"MIA",PQ_GL_Data!$E:$E,"1300",PQ_GL_Data!$N:$N,"2025-06") -> 60.84 | E7: =SUMIFS(PQ_GL_Data!$I:$I,PQ_GL_Data!$C:$C,"CHI",PQ_GL_Data!$E:$E,"1300",PQ_GL_Data!$N:$N,"2025-06")-SUMIFS(PQ_GL_Data!$J:$J,PQ_GL_Data!$C:$C,"CHI",PQ_GL_Data!$E:$E,"1300",PQ_GL_Data!$N:$N,"2025-06") -> 0 | F7: =SUMIFS(PQ_GL_Data!$I:$I,PQ_GL_Data!$C:$C,"DAL",PQ_GL_Data!$E:$E,"1300",PQ_GL_Data!$N:$N,"2025-06")-SUMIFS(PQ_GL_Data!$J:$J,PQ_GL_Data!$C:$C,"DAL",PQ_GL_Data!$E:$E,"1300",PQ_GL_Data!$N:$N,"2025-06") -> 0 | G7: =SUM(D7:F7) -> 60.84
A8: 1500 | B8: Fixed Assets, Net | C8: Asset | D8: =SUMIFS(PQ_GL_Data!$I:$I,PQ_GL_Data!$C:$C,"MIA",PQ_GL_Data!$E:$E,"1500",PQ_GL_Data!$N:$N,"2025-06")-SUMIFS(PQ_GL_Data!$J:$J,PQ_GL_Data!$C:$C,"MIA",PQ_GL_Data!$E:$E,"1500",PQ_GL_Data!$N:$N,"2025-06") -> -1100 | E8: =SUMIFS(PQ_GL_Data!$I:$I,PQ_GL_Data!$C:$C,"CHI",PQ_GL_Data!$E:$E,"1500",PQ_GL_Data!$N:$N,"2025-06")-SUMIFS(PQ_GL_Data!$J:$J,PQ_GL_Data!$C:$C,"CHI",PQ_GL_Data!$E:$E,"1500",PQ_GL_Data!$N:$N,"2025-06") -> -682 | F8: =SUMIFS(PQ_GL_Data!$I:$I,PQ_GL_Data!$C:$C,"DAL",PQ_GL_Data!$E:$E,"1500",PQ_GL_Data!$N:$N,"2025-06")-SUMIFS(PQ_GL_Data!$J:$J,PQ_GL_Data!$C:$C,"DAL",PQ_GL_Data!$E:$E,"1500",PQ_GL_Data!$N:$N,"2025-06") -> -605 | G8: =SUM(D8:F8) -> -2387
A9: 2000 | B9: Accounts Payable | C9: Liability | D9: =SUMIFS(PQ_GL_Data!$I:$I,PQ_GL_Data!$C:$C,"MIA",PQ_GL_Data!$E:$E,"2000",PQ_GL_Data!$N:$N,"2025-06")-SUMIFS(PQ_GL_Data!$J:$J,PQ_GL_Data!$C:$C,"MIA",PQ_GL_Data!$E:$E,"2000",PQ_GL_Data!$N:$N,"2025-06") -> -73.69 | E9: =SUMIFS(PQ_GL_Data!$I:$I,PQ_GL_Data!$C:$C,"CHI",PQ_GL_Data!$E:$E,"2000",PQ_GL_Data!$N:$N,"2025-06")-SUMIFS(PQ_GL_Data!$J:$J,PQ_GL_Data!$C:$C,"CHI",PQ_GL_Data!$E:$E,"2000",PQ_GL_Data!$N:$N,"2025-06") -> -107.98 | F9: =SUMIFS(PQ_GL_Data!$I:$I,PQ_GL_Data!$C:$C,"DAL",PQ_GL_Data!$E:$E,"2000",PQ_GL_Data!$N:$N,"2025-06")-SUMIFS(PQ_GL_Data!$J:$J,PQ_GL_Data!$C:$C,"DAL",PQ_GL_Data!$E:$E,"2000",PQ_GL_Data!$N:$N,"2025-06") -> -63.51 | G9: =SUM(D9:F9) -> -245.18
A10: 2100 | B10: Accrued Payroll | C10: Liability | D10: =SUMIFS(PQ_GL_Data!$I:$I,PQ_GL_Data!$C:$C,"MIA",PQ_GL_Data!$E:$E,"2100",PQ_GL_Data!$N:$N,"2025-06")-SUMIFS(PQ_GL_Data!$J:$J,PQ_GL_Data!$C:$C,"MIA",PQ_GL_Data!$E:$E,"2100",PQ_GL_Data!$N:$N,"2025-06") -> -56.09 | E10: =SUMIFS(PQ_GL_Data!$I:$I,PQ_GL_Data!$C:$C,"CHI",PQ_GL_Data!$E:$E,"2100",PQ_GL_Data!$N:$N,"2025-06")-SUMIFS(PQ_GL_Data!$J:$J,PQ_GL_Data!$C:$C,"CHI",PQ_GL_Data!$E:$E,"2100",PQ_GL_Data!$N:$N,"2025-06") -> -34.78 | F10: =SUMIFS(PQ_GL_Data!$I:$I,PQ_GL_Data!$C:$C,"DAL",PQ_GL_Data!$E:$E,"2100",PQ_GL_Data!$N:$N,"2025-06")-SUMIFS(PQ_GL_Data!$J:$J,PQ_GL_Data!$C:$C,"DAL",PQ_GL_Data!$E:$E,"2100",PQ_GL_Data!$N:$N,"2025-06") -> -30.85 | G10: =SUM(D10:F10) -> -121.72
A11: 2200 | B11: Intercompany Payable | C11: Liability | D11: =SUMIFS(PQ_GL_Data!$I:$I,PQ_GL_Data!$C:$C,"MIA",PQ_GL_Data!$E:$E,"2200",PQ_GL_Data!$N:$N,"2025-06")-SUMIFS(PQ_GL_Data!$J:$J,PQ_GL_Data!$C:$C,"MIA",PQ_GL_Data!$E:$E,"2200",PQ_GL_Data!$N:$N,"2025-06") -> 0 | E11: =SUMIFS(PQ_GL_Data!$I:$I,PQ_GL_Data!$C:$C,"CHI",PQ_GL_Data!$E:$E,"2200",PQ_GL_Data!$N:$N,"2025-06")-SUMIFS(PQ_GL_Data!$J:$J,PQ_GL_Data!$C:$C,"CHI",PQ_GL_Data!$E:$E,"2200",PQ_GL_Data!$N:$N,"2025-06") -> -32.24 | F11: =SUMIFS(PQ_GL_Data!$I:$I,PQ_GL_Data!$C:$C,"DAL",PQ_GL_Data!$E:$E,"2200",PQ_GL_Data!$N:$N,"2025-06")-SUMIFS(PQ_GL_Data!$J:$J,PQ_GL_Data!$C:$C,"DAL",PQ_GL_Data!$E:$E,"2200",PQ_GL_Data!$N:$N,"2025-06") -> -28.6 | G11: =SUM(D11:F11) -> -60.84
A12: 3000 | B12: Owner's Equity / Retained Earnings | C12: Equity | D12: =SUMIFS(PQ_GL_Data!$I:$I,PQ_GL_Data!$C:$C,"MIA",PQ_GL_Data!$E:$E,"3000",PQ_GL_Data!$N:$N,"2025-06")-SUMIFS(PQ_GL_Data!$J:$J,PQ_GL_Data!$C:$C,"MIA",PQ_GL_Data!$E:$E,"3000",PQ_GL_Data!$N:$N,"2025-06") -> 0 | E12: =SUMIFS(PQ_GL_Data!$I:$I,PQ_GL_Data!$C:$C,"CHI",PQ_GL_Data!$E:$E,"3000",PQ_GL_Data!$N:$N,"2025-06")-SUMIFS(PQ_GL_Data!$J:$J,PQ_GL_Data!$C:$C,"CHI",PQ_GL_Data!$E:$E,"3000",PQ_GL_Data!$N:$N,"2025-06") -> 0 | F12: =SUMIFS(PQ_GL_Data!$I:$I,PQ_GL_Data!$C:$C,"DAL",PQ_GL_Data!$E:$E,"3000",PQ_GL_Data!$N:$N,"2025-06")-SUMIFS(PQ_GL_Data!$J:$J,PQ_GL_Data!$C:$C,"DAL",PQ_GL_Data!$E:$E,"3000",PQ_GL_Data!$N:$N,"2025-06") -> 0 | G12: =SUM(D12:F12) -> 0
A13: 4000 | B13: Legal Fee Revenue | C13: Revenue | D13: =SUMIFS(PQ_GL_Data!$I:$I,PQ_GL_Data!$C:$C,"MIA",PQ_GL_Data!$E:$E,"4000",PQ_GL_Data!$N:$N,"2025-06")-SUMIFS(PQ_GL_Data!$J:$J,PQ_GL_Data!$C:$C,"MIA",PQ_GL_Data!$E:$E,"4000",PQ_GL_Data!$N:$N,"2025-06") -> 0 | E13: =SUMIFS(PQ_GL_Data!$I:$I,PQ_GL_Data!$C:$C,"CHI",PQ_GL_Data!$E:$E,"4000",PQ_GL_Data!$N:$N,"2025-06")-SUMIFS(PQ_GL_Data!$J:$J,PQ_GL_Data!$C:$C,"CHI",PQ_GL_Data!$E:$E,"4000",PQ_GL_Data!$N:$N,"2025-06") -> 0 | F13: =SUMIFS(PQ_GL_Data!$I:$I,PQ_GL_Data!$C:$C,"DAL",PQ_GL_Data!$E:$E,"4000",PQ_GL_Data!$N:$N,"2025-06")-SUMIFS(PQ_GL_Data!$J:$J,PQ_GL_Data!$C:$C,"DAL",PQ_GL_Data!$E:$E,"4000",PQ_GL_Data!$N:$N,"2025-06") -> 0 | G13: =SUM(D13:F13) -> 0
A14: 4010 | B14: Litigation Fees | C14: Revenue | D14: =SUMIFS(PQ_GL_Data!$I:$I,PQ_GL_Data!$C:$C,"MIA",PQ_GL_Data!$E:$E,"4010",PQ_GL_Data!$N:$N,"2025-06")-SUMIFS(PQ_GL_Data!$J:$J,PQ_GL_Data!$C:$C,"MIA",PQ_GL_Data!$E:$E,"4010",PQ_GL_Data!$N:$N,"2025-06") -> -47822.5 | E14: =SUMIFS(PQ_GL_Data!$I:$I,PQ_GL_Data!$C:$C,"CHI",PQ_GL_Data!$E:$E,"4010",PQ_GL_Data!$N:$N,"2025-06")-SUMIFS(PQ_GL_Data!$J:$J,PQ_GL_Data!$C:$C,"CHI",PQ_GL_Data!$E:$E,"4010",PQ_GL_Data!$N:$N,"2025-06") -> -29360.01 | F14: =SUMIFS(PQ_GL_Data!$I:$I,PQ_GL_Data!$C:$C,"DAL",PQ_GL_Data!$E:$E,"4010",PQ_GL_Data!$N:$N,"2025-06")-SUMIFS(PQ_GL_Data!$J:$J,PQ_GL_Data!$C:$C,"DAL",PQ_GL_Data!$E:$E,"4010",PQ_GL_Data!$N:$N,"2025-06") -> -24038.78 | G14: =SUM(D14:F14) -> -101221.29
A15: 4020 | B15: Corporate & Transactional Fees | C15: Revenue | D15: =SUMIFS(PQ_GL_Data!$I:$I,PQ_GL_Data!$C:$C,"MIA",PQ_GL_Data!$E:$E,"4020",PQ_GL_Data!$N:$N,"2025-06")-SUMIFS(PQ_GL_Data!$J:$J,PQ_GL_Data!$C:$C,"MIA",PQ_GL_Data!$E:$E,"4020",PQ_GL_Data!$N:$N,"2025-06") -> -37574.82 | E15: =SUMIFS(PQ_GL_Data!$I:$I,PQ_GL_Data!$C:$C,"CHI",PQ_GL_Data!$E:$E,"4020",PQ_GL_Data!$N:$N,"2025-06")-SUMIFS(PQ_GL_Data!$J:$J,PQ_GL_Data!$C:$C,"CHI",PQ_GL_Data!$E:$E,"4020",PQ_GL_Data!$N:$N,"2025-06") -> -23068.58 | F15: =SUMIFS(PQ_GL_Data!$I:$I,PQ_GL_Data!$C:$C,"DAL",PQ_GL_Data!$E:$E,"4020",PQ_GL_Data!$N:$N,"2025-06")-SUMIFS(PQ_GL_Data!$J:$J,PQ_GL_Data!$C:$C,"DAL",PQ_GL_Data!$E:$E,"4020",PQ_GL_Data!$N:$N,"2025-06") -> -18887.62 | G15: =SUM(D15:F15) -> -79531.02
A16: 4030 | B16: Family Law Fees | C16: Revenue | D16: =SUMIFS(PQ_GL_Data!$I:$I,PQ_GL_Data!$C:$C,"MIA",PQ_GL_Data!$E:$E,"4030",PQ_GL_Data!$N:$N,"2025-06")-SUMIFS(PQ_GL_Data!$J:$J,PQ_GL_Data!$C:$C,"MIA",PQ_GL_Data!$E:$E,"4030",PQ_GL_Data!$N:$N,"2025-06") -> -28465.78 | E16: =SUMIFS(PQ_GL_Data!$I:$I,PQ_GL_Data!$C:$C,"CHI",PQ_GL_Data!$E:$E,"4030",PQ_GL_Data!$N:$N,"2025-06")-SUMIFS(PQ_GL_Data!$J:$J,PQ_GL_Data!$C:$C,"CHI",PQ_GL_Data!$E:$E,"4030",PQ_GL_Data!$N:$N,"2025-06") -> -17476.19 | F16: =SUMIFS(PQ_GL_Data!$I:$I,PQ_GL_Data!$C:$C,"DAL",PQ_GL_Data!$E:$E,"4030",PQ_GL_Data!$N:$N,"2025-06")-SUMIFS(PQ_GL_Data!$J:$J,PQ_GL_Data!$C:$C,"DAL",PQ_GL_Data!$E:$E,"4030",PQ_GL_Data!$N:$N,"2025-06") -> -14308.8 | G16: =SUM(D16:F16) -> -60250.77
A17: 4090 | B17: Intercompany Shared Services Revenue | C17: Revenue | D17: =SUMIFS(PQ_GL_Data!$I:$I,PQ_GL_Data!$C:$C,"MIA",PQ_GL_Data!$E:$E,"4090",PQ_GL_Data!$N:$N,"2025-06")-SUMIFS(PQ_GL_Data!$J:$J,PQ_GL_Data!$C:$C,"MIA",PQ_GL_Data!$E:$E,"4090",PQ_GL_Data!$N:$N,"2025-06") -> -7118.28 | E17: =SUMIFS(PQ_GL_Data!$I:$I,PQ_GL_Data!$C:$C,"CHI",PQ_GL_Data!$E:$E,"4090",PQ_GL_Data!$N:$N,"2025-06")-SUMIFS(PQ_GL_Data!$J:$J,PQ_GL_Data!$C:$C,"CHI",PQ_GL_Data!$E:$E,"4090",PQ_GL_Data!$N:$N,"2025-06") -> 0 | F17: =SUMIFS(PQ_GL_Data!$I:$I,PQ_GL_Data!$C:$C,"DAL",PQ_GL_Data!$E:$E,"4090",PQ_GL_Data!$N:$N,"2025-06")-SUMIFS(PQ_GL_Data!$J:$J,PQ_GL_Data!$C:$C,"DAL",PQ_GL_Data!$E:$E,"4090",PQ_GL_Data!$N:$N,"2025-06") -> 0 | G17: =SUM(D17:F17) -> -7118.28
A18: 5000 | B18: Direct Case Costs | C18: COGS | D18: =SUMIFS(PQ_GL_Data!$I:$I,PQ_GL_Data!$C:$C,"MIA",PQ_GL_Data!$E:$E,"5000",PQ_GL_Data!$N:$N,"2025-06")-SUMIFS(PQ_GL_Data!$J:$J,PQ_GL_Data!$C:$C,"MIA",PQ_GL_Data!$E:$E,"5000",PQ_GL_Data!$N:$N,"2025-06") -> 0 | E18: =SUMIFS(PQ_GL_Data!$I:$I,PQ_GL_Data!$C:$C,"CHI",PQ_GL_Data!$E:$E,"5000",PQ_GL_Data!$N:$N,"2025-06")-SUMIFS(PQ_GL_Data!$J:$J,PQ_GL_Data!$C:$C,"CHI",PQ_GL_Data!$E:$E,"5000",PQ_GL_Data!$N:$N,"2025-06") -> 0 | F18: =SUMIFS(PQ_GL_Data!$I:$I,PQ_GL_Data!$C:$C,"DAL",PQ_GL_Data!$E:$E,"5000",PQ_GL_Data!$N:$N,"2025-06")-SUMIFS(PQ_GL_Data!$J:$J,PQ_GL_Data!$C:$C,"DAL",PQ_GL_Data!$E:$E,"5000",PQ_GL_Data!$N:$N,"2025-06") -> 0 | G18: =SUM(D18:F18) -> 0
A19: 5010 | B19: Court Filing Fees | C19: COGS | D19: =SUMIFS(PQ_GL_Data!$I:$I,PQ_GL_Data!$C:$C,"MIA",PQ_GL_Data!$E:$E,"5010",PQ_GL_Data!$N:$N,"2025-06")-SUMIFS(PQ_GL_Data!$J:$J,PQ_GL_Data!$C:$C,"MIA",PQ_GL_Data!$E:$E,"5010",PQ_GL_Data!$N:$N,"2025-06") -> 6466.68 | E19: =SUMIFS(PQ_GL_Data!$I:$I,PQ_GL_Data!$C:$C,"CHI",PQ_GL_Data!$E:$E,"5010",PQ_GL_Data!$N:$N,"2025-06")-SUMIFS(PQ_GL_Data!$J:$J,PQ_GL_Data!$C:$C,"CHI",PQ_GL_Data!$E:$E,"5010",PQ_GL_Data!$N:$N,"2025-06") -> 3970.14 | F19: =SUMIFS(PQ_GL_Data!$I:$I,PQ_GL_Data!$C:$C,"DAL",PQ_GL_Data!$E:$E,"5010",PQ_GL_Data!$N:$N,"2025-06")-SUMIFS(PQ_GL_Data!$J:$J,PQ_GL_Data!$C:$C,"DAL",PQ_GL_Data!$E:$E,"5010",PQ_GL_Data!$N:$N,"2025-06") -> 3250.59 | G19: =SUM(D19:F19) -> 13687.41
A20: 5020 | B20: Expert Witness Fees | C20: COGS | D20: =SUMIFS(PQ_GL_Data!$I:$I,PQ_GL_Data!$C:$C,"MIA",PQ_GL_Data!$E:$E,"5020",PQ_GL_Data!$N:$N,"2025-06")-SUMIFS(PQ_GL_Data!$J:$J,PQ_GL_Data!$C:$C,"MIA",PQ_GL_Data!$E:$E,"5020",PQ_GL_Data!$N:$N,"2025-06") -> 5290.92 | E20: =SUMIFS(PQ_GL_Data!$I:$I,PQ_GL_Data!$C:$C,"CHI",PQ_GL_Data!$E:$E,"5020",PQ_GL_Data!$N:$N,"2025-06")-SUMIFS(PQ_GL_Data!$J:$J,PQ_GL_Data!$C:$C,"CHI",PQ_GL_Data!$E:$E,"5020",PQ_GL_Data!$N:$N,"2025-06") -> 3248.29 | F20: =SUMIFS(PQ_GL_Data!$I:$I,PQ_GL_Data!$C:$C,"DAL",PQ_GL_Data!$E:$E,"5020",PQ_GL_Data!$N:$N,"2025-06")-SUMIFS(PQ_GL_Data!$J:$J,PQ_GL_Data!$C:$C,"DAL",PQ_GL_Data!$E:$E,"5020",PQ_GL_Data!$N:$N,"2025-06") -> 2659.57 | G20: =SUM(D20:F20) -> 11198.78
A21: 6000 | B21: Operating Expenses | C21: Opex | D21: =SUMIFS(PQ_GL_Data!$I:$I,PQ_GL_Data!$C:$C,"MIA",PQ_GL_Data!$E:$E,"6000",PQ_GL_Data!$N:$N,"2025-06")-SUMIFS(PQ_GL_Data!$J:$J,PQ_GL_Data!$C:$C,"MIA",PQ_GL_Data!$E:$E,"6000",PQ_GL_Data!$N:$N,"2025-06") -> 0 | E21: =SUMIFS(PQ_GL_Data!$I:$I,PQ_GL_Data!$C:$C,"CHI",PQ_GL_Data!$E:$E,"6000",PQ_GL_Data!$N:$N,"2025-06")-SUMIFS(PQ_GL_Data!$J:$J,PQ_GL_Data!$C:$C,"CHI",PQ_GL_Data!$E:$E,"6000",PQ_GL_Data!$N:$N,"2025-06") -> 0 | F21: =SUMIFS(PQ_GL_Data!$I:$I,PQ_GL_Data!$C:$C,"DAL",PQ_GL_Data!$E:$E,"6000",PQ_GL_Data!$N:$N,"2025-06")-SUMIFS(PQ_GL_Data!$J:$J,PQ_GL_Data!$C:$C,"DAL",PQ_GL_Data!$E:$E,"6000",PQ_GL_Data!$N:$N,"2025-06") -> 0 | G21: =SUM(D21:F21) -> 0
A22: 6010 | B22: Attorney & Staff Payroll | C22: Opex | D22: =SUMIFS(PQ_GL_Data!$I:$I,PQ_GL_Data!$C:$C,"MIA",PQ_GL_Data!$E:$E,"6010",PQ_GL_Data!$N:$N,"2025-06")-SUMIFS(PQ_GL_Data!$J:$J,PQ_GL_Data!$C:$C,"MIA",PQ_GL_Data!$E:$E,"6010",PQ_GL_Data!$N:$N,"2025-06") -> 49364 | E22: =SUMIFS(PQ_GL_Data!$I:$I,PQ_GL_Data!$C:$C,"CHI",PQ_GL_Data!$E:$E,"6010",PQ_GL_Data!$N:$N,"2025-06")-SUMIFS(PQ_GL_Data!$J:$J,PQ_GL_Data!$C:$C,"CHI",PQ_GL_Data!$E:$E,"6010",PQ_GL_Data!$N:$N,"2025-06") -> 30605.68 | F22: =SUMIFS(PQ_GL_Data!$I:$I,PQ_GL_Data!$C:$C,"DAL",PQ_GL_Data!$E:$E,"6010",PQ_GL_Data!$N:$N,"2025-06")-SUMIFS(PQ_GL_Data!$J:$J,PQ_GL_Data!$C:$C,"DAL",PQ_GL_Data!$E:$E,"6010",PQ_GL_Data!$N:$N,"2025-06") -> 27150.2 | G22: =SUM(D22:F22) -> 107119.88
A23: 6020 | B23: Payroll Taxes & Benefits | C23: Opex | D23: =SUMIFS(PQ_GL_Data!$I:$I,PQ_GL_Data!$C:$C,"MIA",PQ_GL_Data!$E:$E,"6020",PQ_GL_Data!$N:$N,"2025-06")-SUMIFS(PQ_GL_Data!$J:$J,PQ_GL_Data!$C:$C,"MIA",PQ_GL_Data!$E:$E,"6020",PQ_GL_Data!$N:$N,"2025-06") -> 6910.96 | E23: =SUMIFS(PQ_GL_Data!$I:$I,PQ_GL_Data!$C:$C,"CHI",PQ_GL_Data!$E:$E,"6020",PQ_GL_Data!$N:$N,"2025-06")-SUMIFS(PQ_GL_Data!$J:$J,PQ_GL_Data!$C:$C,"CHI",PQ_GL_Data!$E:$E,"6020",PQ_GL_Data!$N:$N,"2025-06") -> 4284.8 | F23: =SUMIFS(PQ_GL_Data!$I:$I,PQ_GL_Data!$C:$C,"DAL",PQ_GL_Data!$E:$E,"6020",PQ_GL_Data!$N:$N,"2025-06")-SUMIFS(PQ_GL_Data!$J:$J,PQ_GL_Data!$C:$C,"DAL",PQ_GL_Data!$E:$E,"6020",PQ_GL_Data!$N:$N,"2025-06") -> 3801.03 | G23: =SUM(D23:F23) -> 14996.79
A24: 6030 | B24: Office Rent | C24: Opex | D24: =SUMIFS(PQ_GL_Data!$I:$I,PQ_GL_Data!$C:$C,"MIA",PQ_GL_Data!$E:$E,"6030",PQ_GL_Data!$N:$N,"2025-06")-SUMIFS(PQ_GL_Data!$J:$J,PQ_GL_Data!$C:$C,"MIA",PQ_GL_Data!$E:$E,"6030",PQ_GL_Data!$N:$N,"2025-06") -> 7378 | E24: =SUMIFS(PQ_GL_Data!$I:$I,PQ_GL_Data!$C:$C,"CHI",PQ_GL_Data!$E:$E,"6030",PQ_GL_Data!$N:$N,"2025-06")-SUMIFS(PQ_GL_Data!$J:$J,PQ_GL_Data!$C:$C,"CHI",PQ_GL_Data!$E:$E,"6030",PQ_GL_Data!$N:$N,"2025-06") -> 4574.36 | F24: =SUMIFS(PQ_GL_Data!$I:$I,PQ_GL_Data!$C:$C,"DAL",PQ_GL_Data!$E:$E,"6030",PQ_GL_Data!$N:$N,"2025-06")-SUMIFS(PQ_GL_Data!$J:$J,PQ_GL_Data!$C:$C,"DAL",PQ_GL_Data!$E:$E,"6030",PQ_GL_Data!$N:$N,"2025-06") -> 4057.9 | G24: =SUM(D24:F24) -> 16010.26
A25: 6040 | B25: Marketing & Business Development | C25: Opex | D25: =SUMIFS(PQ_GL_Data!$I:$I,PQ_GL_Data!$C:$C,"MIA",PQ_GL_Data!$E:$E,"6040",PQ_GL_Data!$N:$N,"2025-06")-SUMIFS(PQ_GL_Data!$J:$J,PQ_GL_Data!$C:$C,"MIA",PQ_GL_Data!$E:$E,"6040",PQ_GL_Data!$N:$N,"2025-06") -> 3289.42 | E25: =SUMIFS(PQ_GL_Data!$I:$I,PQ_GL_Data!$C:$C,"CHI",PQ_GL_Data!$E:$E,"6040",PQ_GL_Data!$N:$N,"2025-06")-SUMIFS(PQ_GL_Data!$J:$J,PQ_GL_Data!$C:$C,"CHI",PQ_GL_Data!$E:$E,"6040",PQ_GL_Data!$N:$N,"2025-06") -> 2019.49 | F25: =SUMIFS(PQ_GL_Data!$I:$I,PQ_GL_Data!$C:$C,"DAL",PQ_GL_Data!$E:$E,"6040",PQ_GL_Data!$N:$N,"2025-06")-SUMIFS(PQ_GL_Data!$J:$J,PQ_GL_Data!$C:$C,"DAL",PQ_GL_Data!$E:$E,"6040",PQ_GL_Data!$N:$N,"2025-06") -> 1653.48 | G25: =SUM(D25:F25) -> 6962.39
A26: 6050 | B26: Professional Insurance | C26: Opex | D26: =SUMIFS(PQ_GL_Data!$I:$I,PQ_GL_Data!$C:$C,"MIA",PQ_GL_Data!$E:$E,"6050",PQ_GL_Data!$N:$N,"2025-06")-SUMIFS(PQ_GL_Data!$J:$J,PQ_GL_Data!$C:$C,"MIA",PQ_GL_Data!$E:$E,"6050",PQ_GL_Data!$N:$N,"2025-06") -> 1450 | E26: =SUMIFS(PQ_GL_Data!$I:$I,PQ_GL_Data!$C:$C,"CHI",PQ_GL_Data!$E:$E,"6050",PQ_GL_Data!$N:$N,"2025-06")-SUMIFS(PQ_GL_Data!$J:$J,PQ_GL_Data!$C:$C,"CHI",PQ_GL_Data!$E:$E,"6050",PQ_GL_Data!$N:$N,"2025-06") -> 899 | F26: =SUMIFS(PQ_GL_Data!$I:$I,PQ_GL_Data!$C:$C,"DAL",PQ_GL_Data!$E:$E,"6050",PQ_GL_Data!$N:$N,"2025-06")-SUMIFS(PQ_GL_Data!$J:$J,PQ_GL_Data!$C:$C,"DAL",PQ_GL_Data!$E:$E,"6050",PQ_GL_Data!$N:$N,"2025-06") -> 797.5 | G26: =SUM(D26:F26) -> 3146.5
A27: 6060 | B27: Software & IT | C27: Opex | D27: =SUMIFS(PQ_GL_Data!$I:$I,PQ_GL_Data!$C:$C,"MIA",PQ_GL_Data!$E:$E,"6060",PQ_GL_Data!$N:$N,"2025-06")-SUMIFS(PQ_GL_Data!$J:$J,PQ_GL_Data!$C:$C,"MIA",PQ_GL_Data!$E:$E,"6060",PQ_GL_Data!$N:$N,"2025-06") -> 2457 | E27: =SUMIFS(PQ_GL_Data!$I:$I,PQ_GL_Data!$C:$C,"CHI",PQ_GL_Data!$E:$E,"6060",PQ_GL_Data!$N:$N,"2025-06")-SUMIFS(PQ_GL_Data!$J:$J,PQ_GL_Data!$C:$C,"CHI",PQ_GL_Data!$E:$E,"6060",PQ_GL_Data!$N:$N,"2025-06") -> 1523.34 | F27: =SUMIFS(PQ_GL_Data!$I:$I,PQ_GL_Data!$C:$C,"DAL",PQ_GL_Data!$E:$E,"6060",PQ_GL_Data!$N:$N,"2025-06")-SUMIFS(PQ_GL_Data!$J:$J,PQ_GL_Data!$C:$C,"DAL",PQ_GL_Data!$E:$E,"6060",PQ_GL_Data!$N:$N,"2025-06") -> 1351.35 | G27: =SUM(D27:F27) -> 5331.69
A28: 6070 | B28: Shared Services Allocation (Intercompany) | C28: Opex | D28: =SUMIFS(PQ_GL_Data!$I:$I,PQ_GL_Data!$C:$C,"MIA",PQ_GL_Data!$E:$E,"6070",PQ_GL_Data!$N:$N,"2025-06")-SUMIFS(PQ_GL_Data!$J:$J,PQ_GL_Data!$C:$C,"MIA",PQ_GL_Data!$E:$E,"6070",PQ_GL_Data!$N:$N,"2025-06") -> 0 | E28: =SUMIFS(PQ_GL_Data!$I:$I,PQ_GL_Data!$C:$C,"CHI",PQ_GL_Data!$E:$E,"6070",PQ_GL_Data!$N:$N,"2025-06")-SUMIFS(PQ_GL_Data!$J:$J,PQ_GL_Data!$C:$C,"CHI",PQ_GL_Data!$E:$E,"6070",PQ_GL_Data!$N:$N,"2025-06") -> 3772.08 | F28: =SUMIFS(PQ_GL_Data!$I:$I,PQ_GL_Data!$C:$C,"DAL",PQ_GL_Data!$E:$E,"6070",PQ_GL_Data!$N:$N,"2025-06")-SUMIFS(PQ_GL_Data!$J:$J,PQ_GL_Data!$C:$C,"DAL",PQ_GL_Data!$E:$E,"6070",PQ_GL_Data!$N:$N,"2025-06") -> 3346.2 | G28: =SUM(D28:F28) -> 7118.28
A29: 7000 | B29: Depreciation Expense | C29: Opex | D29: =SUMIFS(PQ_GL_Data!$I:$I,PQ_GL_Data!$C:$C,"MIA",PQ_GL_Data!$E:$E,"7000",PQ_GL_Data!$N:$N,"2025-06")-SUMIFS(PQ_GL_Data!$J:$J,PQ_GL_Data!$C:$C,"MIA",PQ_GL_Data!$E:$E,"7000",PQ_GL_Data!$N:$N,"2025-06") -> 1100 | E29: =SUMIFS(PQ_GL_Data!$I:$I,PQ_GL_Data!$C:$C,"CHI",PQ_GL_Data!$E:$E,"7000",PQ_GL_Data!$N:$N,"2025-06")-SUMIFS(PQ_GL_Data!$J:$J,PQ_GL_Data!$C:$C,"CHI",PQ_GL_Data!$E:$E,"7000",PQ_GL_Data!$N:$N,"2025-06") -> 682 | F29: =SUMIFS(PQ_GL_Data!$I:$I,PQ_GL_Data!$C:$C,"DAL",PQ_GL_Data!$E:$E,"7000",PQ_GL_Data!$N:$N,"2025-06")-SUMIFS(PQ_GL_Data!$J:$J,PQ_GL_Data!$C:$C,"DAL",PQ_GL_Data!$E:$E,"7000",PQ_GL_Data!$N:$N,"2025-06") -> 605 | G29: =SUM(D29:F29) -> 2387
A30: 8000 | B30: Interest Expense | C30: Opex | D30: =SUMIFS(PQ_GL_Data!$I:$I,PQ_GL_Data!$C:$C,"MIA",PQ_GL_Data!$E:$E,"8000",PQ_GL_Data!$N:$N,"2025-06")-SUMIFS(PQ_GL_Data!$J:$J,PQ_GL_Data!$C:$C,"MIA",PQ_GL_Data!$E:$E,"8000",PQ_GL_Data!$N:$N,"2025-06") -> 0 | E30: =SUMIFS(PQ_GL_Data!$I:$I,PQ_GL_Data!$C:$C,"CHI",PQ_GL_Data!$E:$E,"8000",PQ_GL_Data!$N:$N,"2025-06")-SUMIFS(PQ_GL_Data!$J:$J,PQ_GL_Data!$C:$C,"CHI",PQ_GL_Data!$E:$E,"8000",PQ_GL_Data!$N:$N,"2025-06") -> 0 | F30: =SUMIFS(PQ_GL_Data!$I:$I,PQ_GL_Data!$C:$C,"DAL",PQ_GL_Data!$E:$E,"8000",PQ_GL_Data!$N:$N,"2025-06")-SUMIFS(PQ_GL_Data!$J:$J,PQ_GL_Data!$C:$C,"DAL",PQ_GL_Data!$E:$E,"8000",PQ_GL_Data!$N:$N,"2025-06") -> 0 | G30: =SUM(D30:F30) -> 0

Sheet Bank_Reconciliation
A1: Bank Reconciliation — Cash Account — 2025-06
A3: Line Item | B3: MIA | C3: CHI | D3: DAL
A4: Book Cash Movement (per GL, account 1000) | B4: =SUMIFS(PQ_GL_Data!$I:$I,PQ_GL_Data!$C:$C,"MIA",PQ_GL_Data!$E:$E,"1000",PQ_GL_Data!$N:$N,"2025-06")-SUMIFS(PQ_GL_Data!$J:$J,PQ_GL_Data!$C:$C,"MIA",PQ_GL_Data!$E:$E,"1000",PQ_GL_Data!$N:$N,"2025-06") -> 33024.53 | C4: =SUMIFS(PQ_GL_Data!$I:$I,PQ_GL_Data!$C:$C,"CHI",PQ_GL_Data!$E:$E,"1000",PQ_GL_Data!$N:$N,"2025-06")-SUMIFS(PQ_GL_Data!$J:$J,PQ_GL_Data!$C:$C,"CHI",PQ_GL_Data!$E:$E,"1000",PQ_GL_Data!$N:$N,"2025-06") -> 10400.85 | D4: =SUMIFS(PQ_GL_Data!$I:$I,PQ_GL_Data!$C:$C,"DAL",PQ_GL_Data!$E:$E,"1000",PQ_GL_Data!$N:$N,"2025-06")-SUMIFS(PQ_GL_Data!$J:$J,PQ_GL_Data!$C:$C,"DAL",PQ_GL_Data!$E:$E,"1000",PQ_GL_Data!$N:$N,"2025-06") -> 7680.73
A5: Add: Bank-identified items not yet booked (fees, interest) | B5: =SUMIFS(PQ_Bank_Data!$D:$D,PQ_Bank_Data!$B:$B,"MIA",PQ_Bank_Data!$H:$H,"2025-06",PQ_Bank_Data!$F:$F,"Unmatched - Book Adjustment Needed") -> -10 | C5: =SUMIFS(PQ_Bank_Data!$D:$D,PQ_Bank_Data!$B:$B,"CHI",PQ_Bank_Data!$H:$H,"2025-06",PQ_Bank_Data!$F:$F,"Unmatched - Book Adjustment Needed") -> -12.66 | D5: =SUMIFS(PQ_Bank_Data!$D:$D,PQ_Bank_Data!$B:$B,"DAL",PQ_Bank_Data!$H:$H,"2025-06",PQ_Bank_Data!$F:$F,"Unmatched - Book Adjustment Needed") -> -13.15
A6: Adjusted Book Balance | B6: =B4+B5 -> 33014.53 | C6: =C4+C5 -> 10388.19 | D6: =D4+D5 -> 7667.58
A8: Bank Statement Movement | B8: =SUMIFS(PQ_Bank_Data!$D:$D,PQ_Bank_Data!$B:$B,"MIA",PQ_Bank_Data!$H:$H,"2025-06") -> 35646.07 | C8: =SUMIFS(PQ_Bank_Data!$D:$D,PQ_Bank_Data!$B:$B,"CHI",PQ_Bank_Data!$H:$H,"2025-06") -> 12003.78 | D8: =SUMIFS(PQ_Bank_Data!$D:$D,PQ_Bank_Data!$B:$B,"DAL",PQ_Bank_Data!$H:$H,"2025-06") -> 8990.36
A9: Add: Outstanding items (book not yet cleared bank) | B9: =B4-(SUMIFS(PQ_Bank_Data!$D:$D,PQ_Bank_Data!$B:$B,"MIA",PQ_Bank_Data!$H:$H,"2025-06",PQ_Bank_Data!$F:$F,"Matched")) -> -2631.54 | C9: =C4-(SUMIFS(PQ_Bank_Data!$D:$D,PQ_Bank_Data!$B:$B,"CHI",PQ_Bank_Data!$H:$H,"2025-06",PQ_Bank_Data!$F:$F,"Matched")) -> -1615.59 | D9: =D4-(SUMIFS(PQ_Bank_Data!$D:$D,PQ_Bank_Data!$B:$B,"DAL",PQ_Bank_Data!$H:$H,"2025-06",PQ_Bank_Data!$F:$F,"Matched")) -> -1322.78
A10: Adjusted Bank Balance | B10: =B8+B9 -> 33014.53 | C10: =C8+C9 -> 10388.19 | D10: =D8+D9 -> 7667.58
A12: Difference (Adjusted Book − Adjusted Bank) | B12: =B6-B10 -> 0 | C12: =C6-C10 -> 0 | D12: =D6-D10 -> 0

Sheet Consolidation
A1: Group Consolidation — P&L — 2025-06
A3: Line Item | B3: MIA | C3: CHI | D3: DAL | E3: Combined
A4: External Legal Fee Revenue | B4: =SUMIFS(PQ_GL_Data!$J:$J,PQ_GL_Data!$C:$C,"MIA",PQ_GL_Data!$G:$G,"Revenue",PQ_GL_Data!$H:$H,"No",PQ_GL_Data!$N:$N,"2025-06")-SUMIFS(PQ_GL_Data!$I:$I,PQ_GL_Data!$C:$C,"MIA",PQ_GL_Data!$G:$G,"Revenue",PQ_GL_Data!$H:$H,"No",PQ_GL_Data!$N:$N,"2025-06") -> 113863.1 | C4: =SUMIFS(PQ_GL_Data!$J:$J,PQ_GL_Data!$C:$C,"CHI",PQ_GL_Data!$G:$G,"Revenue",PQ_GL_Data!$H:$H,"No",PQ_GL_Data!$N:$N,"2025-06")-SUMIFS(PQ_GL_Data!$I:$I,PQ_GL_Data!$C:$C,"CHI",PQ_GL_Data!$G:$G,"Revenue",PQ_GL_Data!$H:$H,"No",PQ_GL_Data!$N:$N,"2025-06") -> 69904.78 | D4: =SUMIFS(PQ_GL_Data!$J:$J,PQ_GL_Data!$C:$C,"DAL",PQ_GL_Data!$G:$G,"Revenue",PQ_GL_Data!$H:$H,"No",PQ_GL_Data!$N:$N,"2025-06")-SUMIFS(PQ_GL_Data!$I:$I,PQ_GL_Data!$C:$C,"DAL",PQ_GL_Data!$G:$G,"Revenue",PQ_GL_Data!$H:$H,"No",PQ_GL_Data!$N:$N,"2025-06") -> 57235.2 | E4: =SUM(B4:D4) -> 241003.08
A5: Intercompany Shared Services Revenue | B5: =SUMIFS(PQ_GL_Data!$J:$J,PQ_GL_Data!$C:$C,"MIA",PQ_GL_Data!$G:$G,"Revenue",PQ_GL_Data!$H:$H,"Yes",PQ_GL_Data!$N:$N,"2025-06")-SUMIFS(PQ_GL_Data!$I:$I,PQ_GL_Data!$C:$C,"MIA",PQ_GL_Data!$G:$G,"Revenue",PQ_GL_Data!$H:$H,"Yes",PQ_GL_Data!$N:$N,"2025-06") -> 7118.28 | C5: =SUMIFS(PQ_GL_Data!$J:$J,PQ_GL_Data!$C:$C,"CHI",PQ_GL_Data!$G:$G,"Revenue",PQ_GL_Data!$H:$H,"Yes",PQ_GL_Data!$N:$N,"2025-06")-SUMIFS(PQ_GL_Data!$I:$I,PQ_GL_Data!$C:$C,"CHI",PQ_GL_Data!$G:$G,"Revenue",PQ_GL_Data!$H:$H,"Yes",PQ_GL_Data!$N:$N,"2025-06") -> 0 | D5: =SUMIFS(PQ_GL_Data!$J:$J,PQ_GL_Data!$C:$C,"DAL",PQ_GL_Data!$G:$G,"Revenue",PQ_GL_Data!$H:$H,"Yes",PQ_GL_Data!$N:$N,"2025-06")-SUMIFS(PQ_GL_Data!$I:$I,PQ_GL_Data!$C:$C,"DAL",PQ_GL_Data!$G:$G,"Revenue",PQ_GL_Data!$H:$H,"Yes",PQ_GL_Data!$N:$N,"2025-06") -> 0 | E5: =SUM(B5:D5) -> 7118.28
A6: Total Revenue (Gross) | B6: =B4+B5 -> 120981.38 | C6: =C4+C5 -> 69904.78 | D6: =D4+D5 -> 57235.2 | E6: =E4+E5 -> 248121.36
A7: Direct Case Costs (COGS) | B7: =SUMIFS(PQ_GL_Data!$I:$I,PQ_GL_Data!$C:$C,"MIA",PQ_GL_Data!$G:$G,"COGS",PQ_GL_Data!$N:$N,"2025-06")-SUMIFS(PQ_GL_Data!$J:$J,PQ_GL_Data!$C:$C,"MIA",PQ_GL_Data!$G:$G,"COGS",PQ_GL_Data!$N:$N,"2025-06") -> 11757.6 | C7: =SUMIFS(PQ_GL_Data!$I:$I,PQ_GL_Data!$C:$C,"CHI",PQ_GL_Data!$G:$G,"COGS",PQ_GL_Data!$N:$N,"2025-06")-SUMIFS(PQ_GL_Data!$J:$J,PQ_GL_Data!$C:$C,"CHI",PQ_GL_Data!$G:$G,"COGS",PQ_GL_Data!$N:$N,"2025-06") -> 7218.43 | D7: =SUMIFS(PQ_GL_Data!$I:$I,PQ_GL_Data!$C:$C,"DAL",PQ_GL_Data!$G:$G,"COGS",PQ_GL_Data!$N:$N,"2025-06")-SUMIFS(PQ_GL_Data!$J:$J,PQ_GL_Data!$C:$C,"DAL",PQ_GL_Data!$G:$G,"COGS",PQ_GL_Data!$N:$N,"2025-06") -> 5910.16 | E7: =SUM(B7:D7) -> 24886.19
A8: Gross Profit | B8: =B6-B7 -> 109223.78 | C8: =C6-C7 -> 62686.35 | D8: =D6-D7 -> 51325.04 | E8: =E6-E7 -> 223235.17
A10: Attorney & Staff Payroll | B10: =SUMIFS(PQ_GL_Data!$I:$I,PQ_GL_Data!$C:$C,"MIA",PQ_GL_Data!$E:$E,"6010",PQ_GL_Data!$N:$N,"2025-06")-SUMIFS(PQ_GL_Data!$J:$J,PQ_GL_Data!$C:$C,"MIA",PQ_GL_Data!$E:$E,"6010",PQ_GL_Data!$N:$N,"2025-06") -> 49364 | C10: =SUMIFS(PQ_GL_Data!$I:$I,PQ_GL_Data!$C:$C,"CHI",PQ_GL_Data!$E:$E,"6010",PQ_GL_Data!$N:$N,"2025-06")-SUMIFS(PQ_GL_Data!$J:$J,PQ_GL_Data!$C:$C,"CHI",PQ_GL_Data!$E:$E,"6010",PQ_GL_Data!$N:$N,"2025-06") -> 30605.68 | D10: =SUMIFS(PQ_GL_Data!$I:$I,PQ_GL_Data!$C:$C,"DAL",PQ_GL_Data!$E:$E,"6010",PQ_GL_Data!$N:$N,"2025-06")-SUMIFS(PQ_GL_Data!$J:$J,PQ_GL_Data!$C:$C,"DAL",PQ_GL_Data!$E:$E,"6010",PQ_GL_Data!$N:$N,"2025-06") -> 27150.2 | E10: =SUM(B10:D10) -> 107119.88
A11: Payroll Taxes & Benefits | B11: =SUMIFS(PQ_GL_Data!$I:$I,PQ_GL_Data!$C:$C,"MIA",PQ_GL_Data!$E:$E,"6020",PQ_GL_Data!$N:$N,"2025-06")-SUMIFS(PQ_GL_Data!$J:$J,PQ_GL_Data!$C:$C,"MIA",PQ_GL_Data!$E:$E,"6020",PQ_GL_Data!$N:$N,"2025-06") -> 6910.96 | C11: =SUMIFS(PQ_GL_Data!$I:$I,PQ_GL_Data!$C:$C,"CHI",PQ_GL_Data!$E:$E,"6020",PQ_GL_Data!$N:$N,"2025-06")-SUMIFS(PQ_GL_Data!$J:$J,PQ_GL_Data!$C:$C,"CHI",PQ_GL_Data!$E:$E,"6020",PQ_GL_Data!$N:$N,"2025-06") -> 4284.8 | D11: =SUMIFS(PQ_GL_Data!$I:$I,PQ_GL_Data!$C:$C,"DAL",PQ_GL_Data!$E:$E,"6020",PQ_GL_Data!$N:$N,"2025-06")-SUMIFS(PQ_GL_Data!$J:$J,PQ_GL_Data!$C:$C,"DAL",PQ_GL_Data!$E:$E,"6020",PQ_GL_Data!$N:$N,"2025-06") -> 3801.03 | E11: =SUM(B11:D11) -> 14996.79
A12: Office Rent | B12: =SUMIFS(PQ_GL_Data!$I:$I,PQ_GL_Data!$C:$C,"MIA",PQ_GL_Data!$E:$E,"6030",PQ_GL_Data!$N:$N,"2025-06")-SUMIFS(PQ_GL_Data!$J:$J,PQ_GL_Data!$C:$C,"MIA",PQ_GL_Data!$E:$E,"6030",PQ_GL_Data!$N:$N,"2025-06") -> 7378 | C12: =SUMIFS(PQ_GL_Data!$I:$I,PQ_GL_Data!$C:$C,"CHI",PQ_GL_Data!$E:$E,"6030",PQ_GL_Data!$N:$N,"2025-06")-SUMIFS(PQ_GL_Data!$J:$J,PQ_GL_Data!$C:$C,"CHI",PQ_GL_Data!$E:$E,"6030",PQ_GL_Data!$N:$N,"2025-06") -> 4574.36 | D12: =SUMIFS(PQ_GL_Data!$I:$I,PQ_GL_Data!$C:$C,"DAL",PQ_GL_Data!$E:$E,"6030",PQ_GL_Data!$N:$N,"2025-06")-SUMIFS(PQ_GL_Data!$J:$J,PQ_GL_Data!$C:$C,"DAL",PQ_GL_Data!$E:$E,"6030",PQ_GL_Data!$N:$N,"2025-06") -> 4057.9 | E12: =SUM(B12:D12) -> 16010.26
A13: Marketing & Business Development | B13: =SUMIFS(PQ_GL_Data!$I:$I,PQ_GL_Data!$C:$C,"MIA",PQ_GL_Data!$E:$E,"6040",PQ_GL_Data!$N:$N,"2025-06")-SUMIFS(PQ_GL_Data!$J:$J,PQ_GL_Data!$C:$C,"MIA",PQ_GL_Data!$E:$E,"6040",PQ_GL_Data!$N:$N,"2025-06") -> 3289.42 | C13: =SUMIFS(PQ_GL_Data!$I:$I,PQ_GL_Data!$C:$C,"CHI",PQ_GL_Data!$E:$E,"6040",PQ_GL_Data!$N:$N,"2025-06")-SUMIFS(PQ_GL_Data!$J:$J,PQ_GL_Data!$C:$C,"CHI",PQ_GL_Data!$E:$E,"6040",PQ_GL_Data!$N:$N,"2025-06") -> 2019.49 | D13: =SUMIFS(PQ_GL_Data!$I:$I,PQ_GL_Data!$C:$C,"DAL",PQ_GL_Data!$E:$E,"6040",PQ_GL_Data!$N:$N,"2025-06")-SUMIFS(PQ_GL_Data!$J:$J,PQ_GL_Data!$C:$C,"DAL",PQ_GL_Data!$E:$E,"6040",PQ_GL_Data!$N:$N,"2025-06") -> 1653.48 | E13: =SUM(B13:D13) -> 6962.39
A14: Professional Insurance | B14: =SUMIFS(PQ_GL_Data!$I:$I,PQ_GL_Data!$C:$C,"MIA",PQ_GL_Data!$E:$E,"6050",PQ_GL_Data!$N:$N,"2025-06")-SUMIFS(PQ_GL_Data!$J:$J,PQ_GL_Data!$C:$C,"MIA",PQ_GL_Data!$E:$E,"6050",PQ_GL_Data!$N:$N,"2025-06") -> 1450 | C14: =SUMIFS(PQ_GL_Data!$I:$I,PQ_GL_Data!$C:$C,"CHI",PQ_GL_Data!$E:$E,"6050",PQ_GL_Data!$N:$N,"2025-06")-SUMIFS(PQ_GL_Data!$J:$J,PQ_GL_Data!$C:$C,"CHI",PQ_GL_Data!$E:$E,"6050",PQ_GL_Data!$N:$N,"2025-06") -> 899 | D14: =SUMIFS(PQ_GL_Data!$I:$I,PQ_GL_Data!$C:$C,"DAL",PQ_GL_Data!$E:$E,"6050",PQ_GL_Data!$N:$N,"2025-06")-SUMIFS(PQ_GL_Data!$J:$J,PQ_GL_Data!$C:$C,"DAL",PQ_GL_Data!$E:$E,"6050",PQ_GL_Data!$N:$N,"2025-06") -> 797.5 | E14: =SUM(B14:D14) -> 3146.5
A15: Software & IT | B15: =SUMIFS(PQ_GL_Data!$I:$I,PQ_GL_Data!$C:$C,"MIA",PQ_GL_Data!$E:$E,"6060",PQ_GL_Data!$N:$N,"2025-06")-SUMIFS(PQ_GL_Data!$J:$J,PQ_GL_Data!$C:$C,"MIA",PQ_GL_Data!$E:$E,"6060",PQ_GL_Data!$N:$N,"2025-06") -> 2457 | C15: =SUMIFS(PQ_GL_Data!$I:$I,PQ_GL_Data!$C:$C,"CHI",PQ_GL_Data!$E:$E,"6060",PQ_GL_Data!$N:$N,"2025-06")-SUMIFS(PQ_GL_Data!$J:$J,PQ_GL_Data!$C:$C,"CHI",PQ_GL_Data!$E:$E,"6060",PQ_GL_Data!$N:$N,"2025-06") -> 1523.34 | D15: =SUMIFS(PQ_GL_Data!$I:$I,PQ_GL_Data!$C:$C,"DAL",PQ_GL_Data!$E:$E,"6060",PQ_GL_Data!$N:$N,"2025-06")-SUMIFS(PQ_GL_Data!$J:$J,PQ_GL_Data!$C:$C,"DAL",PQ_GL_Data!$E:$E,"6060",PQ_GL_Data!$N:$N,"2025-06") -> 1351.35 | E15: =SUM(B15:D15) -> 5331.69
A16: Shared Services Allocation (Intercompany) | B16: =SUMIFS(PQ_GL_Data!$I:$I,PQ_GL_Data!$C:$C,"MIA",PQ_GL_Data!$E:$E,"6070",PQ_GL_Data!$N:$N,"2025-06")-SUMIFS(PQ_GL_Data!$J:$J,PQ_GL_Data!$C:$C,"MIA",PQ_GL_Data!$E:$E,"6070",PQ_GL_Data!$N:$N,"2025-06") -> 0 | C16: =SUMIFS(PQ_GL_Data!$I:$I,PQ_GL_Data!$C:$C,"CHI",PQ_GL_Data!$E:$E,"6070",PQ_GL_Data!$N:$N,"2025-06")-SUMIFS(PQ_GL_Data!$J:$J,PQ_GL_Data!$C:$C,"CHI",PQ_GL_Data!$E:$E,"6070",PQ_GL_Data!$N:$N,"2025-06") -> 3772.08 | D16: =SUMIFS(PQ_GL_Data!$I:$I,PQ_GL_Data!$C:$C,"DAL",PQ_GL_Data!$E:$E,"6070",PQ_GL_Data!$N:$N,"2025-06")-SUMIFS(PQ_GL_Data!$J:$J,PQ_GL_Data!$C:$C,"DAL",PQ_GL_Data!$E:$E,"6070",PQ_GL_Data!$N:$N,"2025-06") -> 3346.2 | E16: =SUM(B16:D16) -> 7118.28
A17: Depreciation Expense | B17: =SUMIFS(PQ_GL_Data!$I:$I,PQ_GL_Data!$C:$C,"MIA",PQ_GL_Data!$E:$E,"7000",PQ_GL_Data!$N:$N,"2025-06")-SUMIFS(PQ_GL_Data!$J:$J,PQ_GL_Data!$C:$C,"MIA",PQ_GL_Data!$E:$E,"7000",PQ_GL_Data!$N:$N,"2025-06") -> 1100 | C17: =SUMIFS(PQ_GL_Data!$I:$I,PQ_GL_Data!$C:$C,"CHI",PQ_GL_Data!$E:$E,"7000",PQ_GL_Data!$N:$N,"2025-06")-SUMIFS(PQ_GL_Data!$J:$J,PQ_GL_Data!$C:$C,"CHI",PQ_GL_Data!$E:$E,"7000",PQ_GL_Data!$N:$N,"2025-06") -> 682 | D17: =SUMIFS(PQ_GL_Data!$I:$I,PQ_GL_Data!$C:$C,"DAL",PQ_GL_Data!$E:$E,"7000",PQ_GL_Data!$N:$N,"2025-06")-SUMIFS(PQ_GL_Data!$J:$J,PQ_GL_Data!$C:$C,"DAL",PQ_GL_Data!$E:$E,"7000",PQ_GL_Data!$N:$N,"2025-06") -> 605 | E17: =SUM(B17:D17) -> 2387
A18: Total Operating Expenses (Gross) | B18: =B10+B11+B12+B13+B14+B15+B16+B17 -> 71949.38 | C18: =C10+C11+C12+C13+C14+C15+C16+C17 -> 48360.75 | D18: =D10+D11+D12+D13+D14+D15+D16+D17 -> 42762.66 | E18: =E10+E11+E12+E13+E14+E15+E16+E17 -> 163072.79
A19: Operating Income (Combined, Pre-Elimination) | B19: =B8-B18 -> 37274.4 | C19: =C8-C18 -> 14325.6 | D19: =D8-D18 -> 8562.38 | E19: =E8-E18 -> 60162.38
A21: Consolidation Adjustments
A22: Eliminate: Intercompany Shared Services Revenue | E22: =-E5 -> -7118.28
A23: Eliminate: Intercompany Shared Services Allocation | E23: =-E16 -> -7118.28
A25: Total Revenue (Net of Eliminations) | E25: =E6+E22 -> 241003.08
A26: Total Operating Expenses (Net of Eliminations) | E26: =E18+E23 -> 155954.51
A28: Operating Income (Group, Consolidated) | E28: =E25-E7-E26 -> 60162.38
A30: Note: eliminating the intercompany shared-services billing reduces both Group revenue and Group operating expense by the same amount, so it does not change Operating Income - there is no markup on the intercompany charge. The elimination still matters: without it, Group revenue and expense are both overstated, which misleads any margin-% or expense-ratio analysis.

Sheet Budget_vs_Actual
A1: Budget vs. Actual — 2025-06
A3: Entity | B3: Account | C3: Budget | D3: Actual | E3: Variance (Actual - Budget) | F3: % Variance | G3: Overspend Rank
A4: MIA | B4: 4010 Litigation Fees | C4: =SUMIFS(PQ_Budget_Data!$F:$F,PQ_Budget_Data!$B:$B,"MIA",PQ_Budget_Data!$D:$D,"4010",PQ_Budget_Data!$G:$G,"2025-06") -> 46738.17 | D4: =SUMIFS(PQ_GL_Data!$J:$J,PQ_GL_Data!$C:$C,"MIA",PQ_GL_Data!$E:$E,"4010",PQ_GL_Data!$N:$N,"2025-06")-SUMIFS(PQ_GL_Data!$I:$I,PQ_GL_Data!$C:$C,"MIA",PQ_GL_Data!$E:$E,"4010",PQ_GL_Data!$N:$N,"2025-06") -> 47822.5 | E4: =D4-C4 -> 1084.33 | F4: =IFERROR(E4/C4,0) -> 0.023200095 | G4: =RANK(E4,$E$4:$E$35,0) -> 3
A5: MIA | B5: 4020 Corporate & Transactional Fees | C5: =SUMIFS(PQ_Budget_Data!$F:$F,PQ_Budget_Data!$B:$B,"MIA",PQ_Budget_Data!$D:$D,"4020",PQ_Budget_Data!$G:$G,"2025-06") -> 36939.51 | D5: =SUMIFS(PQ_GL_Data!$J:$J,PQ_GL_Data!$C:$C,"MIA",PQ_GL_Data!$E:$E,"4020",PQ_GL_Data!$N:$N,"2025-06")-SUMIFS(PQ_GL_Data!$I:$I,PQ_GL_Data!$C:$C,"MIA",PQ_GL_Data!$E:$E,"4020",PQ_GL_Data!$N:$N,"2025-06") -> 37574.82 | E5: =D5-C5 -> 635.31 | F5: =IFERROR(E5/C5,0) -> 0.017198658 | G5: =RANK(E5,$E$4:$E$35,0) -> 7
A6: MIA | B6: 4030 Family Law Fees | C6: =SUMIFS(PQ_Budget_Data!$F:$F,PQ_Budget_Data!$B:$B,"MIA",PQ_Budget_Data!$D:$D,"4030",PQ_Budget_Data!$G:$G,"2025-06") -> 27684.41 | D6: =SUMIFS(PQ_GL_Data!$J:$J,PQ_GL_Data!$C:$C,"MIA",PQ_GL_Data!$E:$E,"4030",PQ_GL_Data!$N:$N,"2025-06")-SUMIFS(PQ_GL_Data!$I:$I,PQ_GL_Data!$C:$C,"MIA",PQ_GL_Data!$E:$E,"4030",PQ_GL_Data!$N:$N,"2025-06") -> 28465.78 | E6: =D6-C6 -> 781.37 | F6: =IFERROR(E6/C6,0) -> 0.028224188 | G6: =RANK(E6,$E$4:$E$35,0) -> 5
A7: MIA | B7: 6010 Attorney & Staff Payroll | C7: =SUMIFS(PQ_Budget_Data!$F:$F,PQ_Budget_Data!$B:$B,"MIA",PQ_Budget_Data!$D:$D,"6010",PQ_Budget_Data!$G:$G,"2025-06") -> 48699.54 | D7: =SUMIFS(PQ_GL_Data!$I:$I,PQ_GL_Data!$C:$C,"MIA",PQ_GL_Data!$E:$E,"6010",PQ_GL_Data!$N:$N,"2025-06")-SUMIFS(PQ_GL_Data!$J:$J,PQ_GL_Data!$C:$C,"MIA",PQ_GL_Data!$E:$E,"6010",PQ_GL_Data!$N:$N,"2025-06") -> 49364 | E7: =D7-C7 -> 664.46 | F7: =IFERROR(E7/C7,0) -> 0.013644071 | G7: =RANK(E7,$E$4:$E$35,0) -> 6
A8: MIA | B8: 6020 Payroll Taxes & Benefits | C8: =SUMIFS(PQ_Budget_Data!$F:$F,PQ_Budget_Data!$B:$B,"MIA",PQ_Budget_Data!$D:$D,"6020",PQ_Budget_Data!$G:$G,"2025-06") -> 6946.5 | D8: =SUMIFS(PQ_GL_Data!$I:$I,PQ_GL_Data!$C:$C,"MIA",PQ_GL_Data!$E:$E,"6020",PQ_GL_Data!$N:$N,"2025-06")-SUMIFS(PQ_GL_Data!$J:$J,PQ_GL_Data!$C:$C,"MIA",PQ_GL_Data!$E:$E,"6020",PQ_GL_Data!$N:$N,"2025-06") -> 6910.96 | E8: =D8-C8 -> -35.54 | F8: =IFERROR(E8/C8,0) -> -0.0051162456 | G8: =RANK(E8,$E$4:$E$35,0) -> 27
A9: MIA | B9: 6030 Office Rent | C9: =SUMIFS(PQ_Budget_Data!$F:$F,PQ_Budget_Data!$B:$B,"MIA",PQ_Budget_Data!$D:$D,"6030",PQ_Budget_Data!$G:$G,"2025-06") -> 7310.39 | D9: =SUMIFS(PQ_GL_Data!$I:$I,PQ_GL_Data!$C:$C,"MIA",PQ_GL_Data!$E:$E,"6030",PQ_GL_Data!$N:$N,"2025-06")-SUMIFS(PQ_GL_Data!$J:$J,PQ_GL_Data!$C:$C,"MIA",PQ_GL_Data!$E:$E,"6030",PQ_GL_Data!$N:$N,"2025-06") -> 7378 | E9: =D9-C9 -> 67.61 | F9: =IFERROR(E9/C9,0) -> 0.0092484806 | G9: =RANK(E9,$E$4:$E$35,0) -> 13
A10: MIA | B10: 6040 Marketing & Business Development | C10: =SUMIFS(PQ_Budget_Data!$F:$F,PQ_Budget_Data!$B:$B,"MIA",PQ_Budget_Data!$D:$D,"6040",PQ_Budget_Data!$G:$G,"2025-06") -> 3044.1 | D10: =SUMIFS(PQ_GL_Data!$I:$I,PQ_GL_Data!$C:$C,"MIA",PQ_GL_Data!$E:$E,"6040",PQ_GL_Data!$N:$N,"2025-06")-SUMIFS(PQ_GL_Data!$J:$J,PQ_GL_Data!$C:$C,"MIA",PQ_GL_Data!$E:$E,"6040",PQ_GL_Data!$N:$N,"2025-06") -> 3289.42 | E10: =D10-C10 -> 245.32 | F10: =IFERROR(E10/C10,0) -> 0.08058868 | G10: =RANK(E10,$E$4:$E$35,0) -> 10
A11: MIA | B11: 6050 Professional Insurance | C11: =SUMIFS(PQ_Budget_Data!$F:$F,PQ_Budget_Data!$B:$B,"MIA",PQ_Budget_Data!$D:$D,"6050",PQ_Budget_Data!$G:$G,"2025-06") -> 1428 | D11: =SUMIFS(PQ_GL_Data!$I:$I,PQ_GL_Data!$C:$C,"MIA",PQ_GL_Data!$E:$E,"6050",PQ_GL_Data!$N:$N,"2025-06")-SUMIFS(PQ_GL_Data!$J:$J,PQ_GL_Data!$C:$C,"MIA",PQ_GL_Data!$E:$E,"6050",PQ_GL_Data!$N:$N,"2025-06") -> 1450 | E11: =D11-C11 -> 22 | F11: =IFERROR(E11/C11,0) -> 0.015406162 | G11: =RANK(E11,$E$4:$E$35,0) -> 17
A12: MIA | B12: 6060 Software & IT | C12: =SUMIFS(PQ_Budget_Data!$F:$F,PQ_Budget_Data!$B:$B,"MIA",PQ_Budget_Data!$D:$D,"6060",PQ_Budget_Data!$G:$G,"2025-06") -> 2381.47 | D12: =SUMIFS(PQ_GL_Data!$I:$I,PQ_GL_Data!$C:$C,"MIA",PQ_GL_Data!$E:$E,"6060",PQ_GL_Data!$N:$N,"2025-06")-SUMIFS(PQ_GL_Data!$J:$J,PQ_GL_Data!$C:$C,"MIA",PQ_GL_Data!$E:$E,"6060",PQ_GL_Data!$N:$N,"2025-06") -> 2457 | E12: =D12-C12 -> 75.53 | F12: =IFERROR(E12/C12,0) -> 0.031715705 | G12: =RANK(E12,$E$4:$E$35,0) -> 12
A13: MIA | B13: 7000 Depreciation Expense | C13: =SUMIFS(PQ_Budget_Data!$F:$F,PQ_Budget_Data!$B:$B,"MIA",PQ_Budget_Data!$D:$D,"7000",PQ_Budget_Data!$G:$G,"2025-06") -> 1083.26 | D13: =SUMIFS(PQ_GL_Data!$I:$I,PQ_GL_Data!$C:$C,"MIA",PQ_GL_Data!$E:$E,"7000",PQ_GL_Data!$N:$N,"2025-06")-SUMIFS(PQ_GL_Data!$J:$J,PQ_GL_Data!$C:$C,"MIA",PQ_GL_Data!$E:$E,"7000",PQ_GL_Data!$N:$N,"2025-06") -> 1100 | E13: =D13-C13 -> 16.74 | F13: =IFERROR(E13/C13,0) -> 0.015453354 | G13: =RANK(E13,$E$4:$E$35,0) -> 18
A14: CHI | B14: 4010 Litigation Fees | C14: =SUMIFS(PQ_Budget_Data!$F:$F,PQ_Budget_Data!$B:$B,"CHI",PQ_Budget_Data!$D:$D,"4010",PQ_Budget_Data!$G:$G,"2025-06") -> 29542.6 | D14: =SUMIFS(PQ_GL_Data!$J:$J,PQ_GL_Data!$C:$C,"CHI",PQ_GL_Data!$E:$E,"4010",PQ_GL_Data!$N:$N,"2025-06")-SUMIFS(PQ_GL_Data!$I:$I,PQ_GL_Data!$C:$C,"CHI",PQ_GL_Data!$E:$E,"4010",PQ_GL_Data!$N:$N,"2025-06") -> 29360.01 | E14: =D14-C14 -> -182.59 | F14: =IFERROR(E14/C14,0) -> -0.0061805664 | G14: =RANK(E14,$E$4:$E$35,0) -> 30
A15: CHI | B15: 4020 Corporate & Transactional Fees | C15: =SUMIFS(PQ_Budget_Data!$F:$F,PQ_Budget_Data!$B:$B,"CHI",PQ_Budget_Data!$D:$D,"4020",PQ_Budget_Data!$G:$G,"2025-06") -> 21880.89 | D15: =SUMIFS(PQ_GL_Data!$J:$J,PQ_GL_Data!$C:$C,"CHI",PQ_GL_Data!$E:$E,"4020",PQ_GL_Data!$N:$N,"2025-06")-SUMIFS(PQ_GL_Data!$I:$I,PQ_GL_Data!$C:$C,"CHI",PQ_GL_Data!$E:$E,"4020",PQ_GL_Data!$N:$N,"2025-06") -> 23068.58 | E15: =D15-C15 -> 1187.69 | F15: =IFERROR(E15/C15,0) -> 0.054279785 | G15: =RANK(E15,$E$4:$E$35,0) -> 2
A16: CHI | B16: 4030 Family Law Fees | C16: =SUMIFS(PQ_Budget_Data!$F:$F,PQ_Budget_Data!$B:$B,"CHI",PQ_Budget_Data!$D:$D,"4030",PQ_Budget_Data!$G:$G,"2025-06") -> 16631.01 | D16: =SUMIFS(PQ_GL_Data!$J:$J,PQ_GL_Data!$C:$C,"CHI",PQ_GL_Data!$E:$E,"4030",PQ_GL_Data!$N:$N,"2025-06")-SUMIFS(PQ_GL_Data!$I:$I,PQ_GL_Data!$C:$C,"CHI",PQ_GL_Data!$E:$E,"4030",PQ_GL_Data!$N:$N,"2025-06") -> 17476.19 | E16: =D16-C16 -> 845.18 | F16: =IFERROR(E16/C16,0) -> 0.050819523 | G16: =RANK(E16,$E$4:$E$35,0) -> 4
A17: CHI | B17: 6010 Attorney & Staff Payroll | C17: =SUMIFS(PQ_Budget_Data!$F:$F,PQ_Budget_Data!$B:$B,"CHI",PQ_Budget_Data!$D:$D,"6010",PQ_Budget_Data!$G:$G,"2025-06") -> 30796.33 | D17: =SUMIFS(PQ_GL_Data!$I:$I,PQ_GL_Data!$C:$C,"CHI",PQ_GL_Data!$E:$E,"6010",PQ_GL_Data!$N:$N,"2025-06")-SUMIFS(PQ_GL_Data!$J:$J,PQ_GL_Data!$C:$C,"CHI",PQ_GL_Data!$E:$E,"6010",PQ_GL_Data!$N:$N,"2025-06") -> 30605.68 | E17: =D17-C17 -> -190.65 | F17: =IFERROR(E17/C17,0) -> -0.0061906727 | G17: =RANK(E17,$E$4:$E$35,0) -> 32
A18: CHI | B18: 6020 Payroll Taxes & Benefits | C18: =SUMIFS(PQ_Budget_Data!$F:$F,PQ_Budget_Data!$B:$B,"CHI",PQ_Budget_Data!$D:$D,"6020",PQ_Budget_Data!$G:$G,"2025-06") -> 4365.48 | D18: =SUMIFS(PQ_GL_Data!$I:$I,PQ_GL_Data!$C:$C,"CHI",PQ_GL_Data!$E:$E,"6020",PQ_GL_Data!$N:$N,"2025-06")-SUMIFS(PQ_GL_Data!$J:$J,PQ_GL_Data!$C:$C,"CHI",PQ_GL_Data!$E:$E,"6020",PQ_GL_Data!$N:$N,"2025-06") -> 4284.8 | E18: =D18-C18 -> -80.68 | F18: =IFERROR(E18/C18,0) -> -0.018481358 | G18: =RANK(E18,$E$4:$E$35,0) -> 29
A19: CHI | B19: 6030 Office Rent | C19: =SUMIFS(PQ_Budget_Data!$F:$F,PQ_Budget_Data!$B:$B,"CHI",PQ_Budget_Data!$D:$D,"6030",PQ_Budget_Data!$G:$G,"2025-06") -> 4578.87 | D19: =SUMIFS(PQ_GL_Data!$I:$I,PQ_GL_Data!$C:$C,"CHI",PQ_GL_Data!$E:$E,"6030",PQ_GL_Data!$N:$N,"2025-06")-SUMIFS(PQ_GL_Data!$J:$J,PQ_GL_Data!$C:$C,"CHI",PQ_GL_Data!$E:$E,"6030",PQ_GL_Data!$N:$N,"2025-06") -> 4574.36 | E19: =D19-C19 -> -4.51 | F19: =IFERROR(E19/C19,0) -> -0.00098495917 | G19: =RANK(E19,$E$4:$E$35,0) -> 25
A20: CHI | B20: 6040 Marketing & Business Development | C20: =SUMIFS(PQ_Budget_Data!$F:$F,PQ_Budget_Data!$B:$B,"CHI",PQ_Budget_Data!$D:$D,"6040",PQ_Budget_Data!$G:$G,"2025-06") -> 1888.02 | D20: =SUMIFS(PQ_GL_Data!$I:$I,PQ_GL_Data!$C:$C,"CHI",PQ_GL_Data!$E:$E,"6040",PQ_GL_Data!$N:$N,"2025-06")-SUMIFS(PQ_GL_Data!$J:$J,PQ_GL_Data!$C:$C,"CHI",PQ_GL_Data!$E:$E,"6040",PQ_GL_Data!$N:$N,"2025-06") -> 2019.49 | E20: =D20-C20 -> 131.47 | F20: =IFERROR(E20/C20,0) -> 0.069633796 | G20: =RANK(E20,$E$4:$E$35,0) -> 11
A21: CHI | B21: 6050 Professional Insurance | C21: =SUMIFS(PQ_Budget_Data!$F:$F,PQ_Budget_Data!$B:$B,"CHI",PQ_Budget_Data!$D:$D,"6050",PQ_Budget_Data!$G:$G,"2025-06") -> 884.63 | D21: =SUMIFS(PQ_GL_Data!$I:$I,PQ_GL_Data!$C:$C,"CHI",PQ_GL_Data!$E:$E,"6050",PQ_GL_Data!$N:$N,"2025-06")-SUMIFS(PQ_GL_Data!$J:$J,PQ_GL_Data!$C:$C,"CHI",PQ_GL_Data!$E:$E,"6050",PQ_GL_Data!$N:$N,"2025-06") -> 899 | E21: =D21-C21 -> 14.37 | F21: =IFERROR(E21/C21,0) -> 0.016244079 | G21: =RANK(E21,$E$4:$E$35,0) -> 19
A22: CHI | B22: 6060 Software & IT | C22: =SUMIFS(PQ_Budget_Data!$F:$F,PQ_Budget_Data!$B:$B,"CHI",PQ_Budget_Data!$D:$D,"6060",PQ_Budget_Data!$G:$G,"2025-06") -> 1476.74 | D22: =SUMIFS(PQ_GL_Data!$I:$I,PQ_GL_Data!$C:$C,"CHI",PQ_GL_Data!$E:$E,"6060",PQ_GL_Data!$N:$N,"2025-06")-SUMIFS(PQ_GL_Data!$J:$J,PQ_GL_Data!$C:$C,"CHI",PQ_GL_Data!$E:$E,"6060",PQ_GL_Data!$N:$N,"2025-06") -> 1523.34 | E22: =D22-C22 -> 46.6 | F22: =IFERROR(E22/C22,0) -> 0.031555995 | G22: =RANK(E22,$E$4:$E$35,0) -> 16
A23: CHI | B23: 6070 Shared Services Allocation (Intercompany) | C23: =SUMIFS(PQ_Budget_Data!$F:$F,PQ_Budget_Data!$B:$B,"CHI",PQ_Budget_Data!$D:$D,"6070",PQ_Budget_Data!$G:$G,"2025-06") -> 3772.08 | D23: =SUMIFS(PQ_GL_Data!$I:$I,PQ_GL_Data!$C:$C,"CHI",PQ_GL_Data!$E:$E,"6070",PQ_GL_Data!$N:$N,"2025-06")-SUMIFS(PQ_GL_Data!$J:$J,PQ_GL_Data!$C:$C,"CHI",PQ_GL_Data!$E:$E,"6070",PQ_GL_Data!$N:$N,"2025-06") -> 3772.08 | E23: =D23-C23 -> 0 | F23: =IFERROR(E23/C23,0) -> 0 | G23: =RANK(E23,$E$4:$E$35,0) -> 22
A24: CHI | B24: 7000 Depreciation Expense | C24: =SUMIFS(PQ_Budget_Data!$F:$F,PQ_Budget_Data!$B:$B,"CHI",PQ_Budget_Data!$D:$D,"7000",PQ_Budget_Data!$G:$G,"2025-06") -> 674.57 | D24: =SUMIFS(PQ_GL_Data!$I:$I,PQ_GL_Data!$C:$C,"CHI",PQ_GL_Data!$E:$E,"7000",PQ_GL_Data!$N:$N,"2025-06")-SUMIFS(PQ_GL_Data!$J:$J,PQ_GL_Data!$C:$C,"CHI",PQ_GL_Data!$E:$E,"7000",PQ_GL_Data!$N:$N,"2025-06") -> 682 | E24: =D24-C24 -> 7.43 | F24: =IFERROR(E24/C24,0) -> 0.011014424 | G24: =RANK(E24,$E$4:$E$35,0) -> 20
A25: DAL | B25: 4010 Litigation Fees | C25: =SUMIFS(PQ_Budget_Data!$F:$F,PQ_Budget_Data!$B:$B,"DAL",PQ_Budget_Data!$D:$D,"4010",PQ_Budget_Data!$G:$G,"2025-06") -> 22390.08 | D25: =SUMIFS(PQ_GL_Data!$J:$J,PQ_GL_Data!$C:$C,"DAL",PQ_GL_Data!$E:$E,"4010",PQ_GL_Data!$N:$N,"2025-06")-SUMIFS(PQ_GL_Data!$I:$I,PQ_GL_Data!$C:$C,"DAL",PQ_GL_Data!$E:$E,"4010",PQ_GL_Data!$N:$N,"2025-06") -> 24038.78 | E25: =D25-C25 -> 1648.7 | F25: =IFERROR(E25/C25,0) -> 0.073635288 | G25: =RANK(E25,$E$4:$E$35,0) -> 1
A26: DAL | B26: 4020 Corporate & Transactional Fees | C26: =SUMIFS(PQ_Budget_Data!$F:$F,PQ_Budget_Data!$B:$B,"DAL",PQ_Budget_Data!$D:$D,"4020",PQ_Budget_Data!$G:$G,"2025-06") -> 18574.34 | D26: =SUMIFS(PQ_GL_Data!$J:$J,PQ_GL_Data!$C:$C,"DAL",PQ_GL_Data!$E:$E,"4020",PQ_GL_Data!$N:$N,"2025-06")-SUMIFS(PQ_GL_Data!$I:$I,PQ_GL_Data!$C:$C,"DAL",PQ_GL_Data!$E:$E,"4020",PQ_GL_Data!$N:$N,"2025-06") -> 18887.62 | E26: =D26-C26 -> 313.28 | F26: =IFERROR(E26/C26,0) -> 0.016866279 | G26: =RANK(E26,$E$4:$E$35,0) -> 9
A27: DAL | B27: 4030 Family Law Fees | C27: =SUMIFS(PQ_Budget_Data!$F:$F,PQ_Budget_Data!$B:$B,"DAL",PQ_Budget_Data!$D:$D,"4030",PQ_Budget_Data!$G:$G,"2025-06") -> 13699.69 | D27: =SUMIFS(PQ_GL_Data!$J:$J,PQ_GL_Data!$C:$C,"DAL",PQ_GL_Data!$E:$E,"4030",PQ_GL_Data!$N:$N,"2025-06")-SUMIFS(PQ_GL_Data!$I:$I,PQ_GL_Data!$C:$C,"DAL",PQ_GL_Data!$E:$E,"4030",PQ_GL_Data!$N:$N,"2025-06") -> 14308.8 | E27: =D27-C27 -> 609.11 | F27: =IFERROR(E27/C27,0) -> 0.04446159 | G27: =RANK(E27,$E$4:$E$35,0) -> 8
A28: DAL | B28: 6010 Attorney & Staff Payroll | C28: =SUMIFS(PQ_Budget_Data!$F:$F,PQ_Budget_Data!$B:$B,"DAL",PQ_Budget_Data!$D:$D,"6010",PQ_Budget_Data!$G:$G,"2025-06") -> 27086.88 | D28: =SUMIFS(PQ_GL_Data!$I:$I,PQ_GL_Data!$C:$C,"DAL",PQ_GL_Data!$E:$E,"6010",PQ_GL_Data!$N:$N,"2025-06")-SUMIFS(PQ_GL_Data!$J:$J,PQ_GL_Data!$C:$C,"DAL",PQ_GL_Data!$E:$E,"6010",PQ_GL_Data!$N:$N,"2025-06") -> 27150.2 | E28: =D28-C28 -> 63.32 | F28: =IFERROR(E28/C28,0) -> 0.0023376631 | G28: =RANK(E28,$E$4:$E$35,0) -> 14
A29: DAL | B29: 6020 Payroll Taxes & Benefits | C29: =SUMIFS(PQ_Budget_Data!$F:$F,PQ_Budget_Data!$B:$B,"DAL",PQ_Budget_Data!$D:$D,"6020",PQ_Budget_Data!$G:$G,"2025-06") -> 3819.54 | D29: =SUMIFS(PQ_GL_Data!$I:$I,PQ_GL_Data!$C:$C,"DAL",PQ_GL_Data!$E:$E,"6020",PQ_GL_Data!$N:$N,"2025-06")-SUMIFS(PQ_GL_Data!$J:$J,PQ_GL_Data!$C:$C,"DAL",PQ_GL_Data!$E:$E,"6020",PQ_GL_Data!$N:$N,"2025-06") -> 3801.03 | E29: =D29-C29 -> -18.51 | F29: =IFERROR(E29/C29,0) -> -0.0048461333 | G29: =RANK(E29,$E$4:$E$35,0) -> 26
A30: DAL | B30: 6030 Office Rent | C30: =SUMIFS(PQ_Budget_Data!$F:$F,PQ_Budget_Data!$B:$B,"DAL",PQ_Budget_Data!$D:$D,"6030",PQ_Budget_Data!$G:$G,"2025-06") -> 3997.24 | D30: =SUMIFS(PQ_GL_Data!$I:$I,PQ_GL_Data!$C:$C,"DAL",PQ_GL_Data!$E:$E,"6030",PQ_GL_Data!$N:$N,"2025-06")-SUMIFS(PQ_GL_Data!$J:$J,PQ_GL_Data!$C:$C,"DAL",PQ_GL_Data!$E:$E,"6030",PQ_GL_Data!$N:$N,"2025-06") -> 4057.9 | E30: =D30-C30 -> 60.66 | F30: =IFERROR(E30/C30,0) -> 0.015175471 | G30: =RANK(E30,$E$4:$E$35,0) -> 15
A31: DAL | B31: 6040 Marketing & Business Development | C31: =SUMIFS(PQ_Budget_Data!$F:$F,PQ_Budget_Data!$B:$B,"DAL",PQ_Budget_Data!$D:$D,"6040",PQ_Budget_Data!$G:$G,"2025-06") -> 1836.25 | D31: =SUMIFS(PQ_GL_Data!$I:$I,PQ_GL_Data!$C:$C,"DAL",PQ_GL_Data!$E:$E,"6040",PQ_GL_Data!$N:$N,"2025-06")-SUMIFS(PQ_GL_Data!$J:$J,PQ_GL_Data!$C:$C,"DAL",PQ_GL_Data!$E:$E,"6040",PQ_GL_Data!$N:$N,"2025-06") -> 1653.48 | E31: =D31-C31 -> -182.77 | F31: =IFERROR(E31/C31,0) -> -0.099534377 | G31: =RANK(E31,$E$4:$E$35,0) -> 31
A32: DAL | B32: 6050 Professional Insurance | C32: =SUMIFS(PQ_Budget_Data!$F:$F,PQ_Budget_Data!$B:$B,"DAL",PQ_Budget_Data!$D:$D,"6050",PQ_Budget_Data!$G:$G,"2025-06") -> 797.21 | D32: =SUMIFS(PQ_GL_Data!$I:$I,PQ_GL_Data!$C:$C,"DAL",PQ_GL_Data!$E:$E,"6050",PQ_GL_Data!$N:$N,"2025-06")-SUMIFS(PQ_GL_Data!$J:$J,PQ_GL_Data!$C:$C,"DAL",PQ_GL_Data!$E:$E,"6050",PQ_GL_Data!$N:$N,"2025-06") -> 797.5 | E32: =D32-C32 -> 0.29 | F32: =IFERROR(E32/C32,0) -> 0.00036376864 | G32: =RANK(E32,$E$4:$E$35,0) -> 21
A33: DAL | B33: 6060 Software & IT | C33: =SUMIFS(PQ_Budget_Data!$F:$F,PQ_Budget_Data!$B:$B,"DAL",PQ_Budget_Data!$D:$D,"6060",PQ_Budget_Data!$G:$G,"2025-06") -> 1401.72 | D33: =SUMIFS(PQ_GL_Data!$I:$I,PQ_GL_Data!$C:$C,"DAL",PQ_GL_Data!$E:$E,"6060",PQ_GL_Data!$N:$N,"2025-06")-SUMIFS(PQ_GL_Data!$J:$J,PQ_GL_Data!$C:$C,"DAL",PQ_GL_Data!$E:$E,"6060",PQ_GL_Data!$N:$N,"2025-06") -> 1351.35 | E33: =D33-C33 -> -50.37 | F33: =IFERROR(E33/C33,0) -> -0.035934423 | G33: =RANK(E33,$E$4:$E$35,0) -> 28
A34: DAL | B34: 6070 Shared Services Allocation (Intercompany) | C34: =SUMIFS(PQ_Budget_Data!$F:$F,PQ_Budget_Data!$B:$B,"DAL",PQ_Budget_Data!$D:$D,"6070",PQ_Budget_Data!$G:$G,"2025-06") -> 3346.2 | D34: =SUMIFS(PQ_GL_Data!$I:$I,PQ_GL_Data!$C:$C,"DAL",PQ_GL_Data!$E:$E,"6070",PQ_GL_Data!$N:$N,"2025-06")-SUMIFS(PQ_GL_Data!$J:$J,PQ_GL_Data!$C:$C,"DAL",PQ_GL_Data!$E:$E,"6070",PQ_GL_Data!$N:$N,"2025-06") -> 3346.2 | E34: =D34-C34 -> 0 | F34: =IFERROR(E34/C34,0) -> 0 | G34: =RANK(E34,$E$4:$E$35,0) -> 22
A35: DAL | B35: 7000 Depreciation Expense | C35: =SUMIFS(PQ_Budget_Data!$F:$F,PQ_Budget_Data!$B:$B,"DAL",PQ_Budget_Data!$D:$D,"7000",PQ_Budget_Data!$G:$G,"2025-06") -> 606.79 | D35: =SUMIFS(PQ_GL_Data!$I:$I,PQ_GL_Data!$C:$C,"DAL",PQ_GL_Data!$E:$E,"7000",PQ_GL_Data!$N:$N,"2025-06")-SUMIFS(PQ_GL_Data!$J:$J,PQ_GL_Data!$C:$C,"DAL",PQ_GL_Data!$E:$E,"7000",PQ_GL_Data!$N:$N,"2025-06") -> 605 | E35: =D35-C35 -> -1.79 | F35: =IFERROR(E35/C35,0) -> -0.0029499497 | G35: =RANK(E35,$E$4:$E$35,0) -> 24

Sheet Dashboard_Data
A1: Month | B1: MIA Revenue | C1: CHI Revenue | D1: DAL Revenue | E1: Group Revenue
A2: 2024-01 | B2: =SUMIFS(PQ_GL_Data!$J:$J,PQ_GL_Data!$C:$C,"MIA",PQ_GL_Data!$G:$G,"Revenue",PQ_GL_Data!$H:$H,"No",PQ_GL_Data!$N:$N,"2024-01")-SUMIFS(PQ_GL_Data!$I:$I,PQ_GL_Data!$C:$C,"MIA",PQ_GL_Data!$G:$G,"Revenue",PQ_GL_Data!$H:$H,"No",PQ_GL_Data!$N:$N,"2024-01") -> 95742 | C2: =SUMIFS(PQ_GL_Data!$J:$J,PQ_GL_Data!$C:$C,"CHI",PQ_GL_Data!$G:$G,"Revenue",PQ_GL_Data!$H:$H,"No",PQ_GL_Data!$N:$N,"2024-01")-SUMIFS(PQ_GL_Data!$I:$I,PQ_GL_Data!$C:$C,"CHI",PQ_GL_Data!$G:$G,"Revenue",PQ_GL_Data!$H:$H,"No",PQ_GL_Data!$N:$N,"2024-01") -> 51668.99 | D2: =SUMIFS(PQ_GL_Data!$J:$J,PQ_GL_Data!$C:$C,"DAL",PQ_GL_Data!$G:$G,"Revenue",PQ_GL_Data!$H:$H,"No",PQ_GL_Data!$N:$N,"2024-01")-SUMIFS(PQ_GL_Data!$I:$I,PQ_GL_Data!$C:$C,"DAL",PQ_GL_Data!$G:$G,"Revenue",PQ_GL_Data!$H:$H,"No",PQ_GL_Data!$N:$N,"2024-01") -> 56195.7 | E2: =SUM(B2:D2) -> 203606.69
A3: 2024-02 | B3: =SUMIFS(PQ_GL_Data!$J:$J,PQ_GL_Data!$C:$C,"MIA",PQ_GL_Data!$G:$G,"Revenue",PQ_GL_Data!$H:$H,"No",PQ_GL_Data!$N:$N,"2024-02")-SUMIFS(PQ_GL_Data!$I:$I,PQ_GL_Data!$C:$C,"MIA",PQ_GL_Data!$G:$G,"Revenue",PQ_GL_Data!$H:$H,"No",PQ_GL_Data!$N:$N,"2024-02") -> 100782.2 | C3: =SUMIFS(PQ_GL_Data!$J:$J,PQ_GL_Data!$C:$C,"CHI",PQ_GL_Data!$G:$G,"Revenue",PQ_GL_Data!$H:$H,"No",PQ_GL_Data!$N:$N,"2024-02")-SUMIFS(PQ_GL_Data!$I:$I,PQ_GL_Data!$C:$C,"CHI",PQ_GL_Data!$G:$G,"Revenue",PQ_GL_Data!$H:$H,"No",PQ_GL_Data!$N:$N,"2024-02") -> 60024.83 | D3: =SUMIFS(PQ_GL_Data!$J:$J,PQ_GL_Data!$C:$C,"DAL",PQ_GL_Data!$G:$G,"Revenue",PQ_GL_Data!$H:$H,"No",PQ_GL_Data!$N:$N,"2024-02")-SUMIFS(PQ_GL_Data!$I:$I,PQ_GL_Data!$C:$C,"DAL",PQ_GL_Data!$G:$G,"Revenue",PQ_GL_Data!$H:$H,"No",PQ_GL_Data!$N:$N,"2024-02") -> 57234.04 | E3: =SUM(B3:D3) -> 218041.07
A4: 2024-03 | B4: =SUMIFS(PQ_GL_Data!$J:$J,PQ_GL_Data!$C:$C,"MIA",PQ_GL_Data!$G:$G,"Revenue",PQ_GL_Data!$H:$H,"No",PQ_GL_Data!$N:$N,"2024-03")-SUMIFS(PQ_GL_Data!$I:$I,PQ_GL_Data!$C:$C,"MIA",PQ_GL_Data!$G:$G,"Revenue",PQ_GL_Data!$H:$H,"No",PQ_GL_Data!$N:$N,"2024-03") -> 102950.59 | C4: =SUMIFS(PQ_GL_Data!$J:$J,PQ_GL_Data!$C:$C,"CHI",PQ_GL_Data!$G:$G,"Revenue",PQ_GL_Data!$H:$H,"No",PQ_GL_Data!$N:$N,"2024-03")-SUMIFS(PQ_GL_Data!$I:$I,PQ_GL_Data!$C:$C,"CHI",PQ_GL_Data!$G:$G,"Revenue",PQ_GL_Data!$H:$H,"No",PQ_GL_Data!$N:$N,"2024-03") -> 57700.35 | D4: =SUMIFS(PQ_GL_Data!$J:$J,PQ_GL_Data!$C:$C,"DAL",PQ_GL_Data!$G:$G,"Revenue",PQ_GL_Data!$H:$H,"No",PQ_GL_Data!$N:$N,"2024-03")-SUMIFS(PQ_GL_Data!$I:$I,PQ_GL_Data!$C:$C,"DAL",PQ_GL_Data!$G:$G,"Revenue",PQ_GL_Data!$H:$H,"No",PQ_GL_Data!$N:$N,"2024-03") -> 57987.91 | E4: =SUM(B4:D4) -> 218638.85
A5: 2024-04 | B5: =SUMIFS(PQ_GL_Data!$J:$J,PQ_GL_Data!$C:$C,"MIA",PQ_GL_Data!$G:$G,"Revenue",PQ_GL_Data!$H:$H,"No",PQ_GL_Data!$N:$N,"2024-04")-SUMIFS(PQ_GL_Data!$I:$I,PQ_GL_Data!$C:$C,"MIA",PQ_GL_Data!$G:$G,"Revenue",PQ_GL_Data!$H:$H,"No",PQ_GL_Data!$N:$N,"2024-04") -> 95294.77 | C5: =SUMIFS(PQ_GL_Data!$J:$J,PQ_GL_Data!$C:$C,"CHI",PQ_GL_Data!$G:$G,"Revenue",PQ_GL_Data!$H:$H,"No",PQ_GL_Data!$N:$N,"2024-04")-SUMIFS(PQ_GL_Data!$I:$I,PQ_GL_Data!$C:$C,"CHI",PQ_GL_Data!$G:$G,"Revenue",PQ_GL_Data!$H:$H,"No",PQ_GL_Data!$N:$N,"2024-04") -> 63097.16 | D5: =SUMIFS(PQ_GL_Data!$J:$J,PQ_GL_Data!$C:$C,"DAL",PQ_GL_Data!$G:$G,"Revenue",PQ_GL_Data!$H:$H,"No",PQ_GL_Data!$N:$N,"2024-04")-SUMIFS(PQ_GL_Data!$I:$I,PQ_GL_Data!$C:$C,"DAL",PQ_GL_Data!$G:$G,"Revenue",PQ_GL_Data!$H:$H,"No",PQ_GL_Data!$N:$N,"2024-04") -> 57305.31 | E5: =SUM(B5:D5) -> 215697.24
A6: 2024-05 | B6: =SUMIFS(PQ_GL_Data!$J:$J,PQ_GL_Data!$C:$C,"MIA",PQ_GL_Data!$G:$G,"Revenue",PQ_GL_Data!$H:$H,"No",PQ_GL_Data!$N:$N,"2024-05")-SUMIFS(PQ_GL_Data!$I:$I,PQ_GL_Data!$C:$C,"MIA",PQ_GL_Data!$G:$G,"Revenue",PQ_GL_Data!$H:$H,"No",PQ_GL_Data!$N:$N,"2024-05") -> 95749.8 | C6: =SUMIFS(PQ_GL_Data!$J:$J,PQ_GL_Data!$C:$C,"CHI",PQ_GL_Data!$G:$G,"Revenue",PQ_GL_Data!$H:$H,"No",PQ_GL_Data!$N:$N,"2024-05")-SUMIFS(PQ_GL_Data!$I:$I,PQ_GL_Data!$C:$C,"CHI",PQ_GL_Data!$G:$G,"Revenue",PQ_GL_Data!$H:$H,"No",PQ_GL_Data!$N:$N,"2024-05") -> 58246.34 | D6: =SUMIFS(PQ_GL_Data!$J:$J,PQ_GL_Data!$C:$C,"DAL",PQ_GL_Data!$G:$G,"Revenue",PQ_GL_Data!$H:$H,"No",PQ_GL_Data!$N:$N,"2024-05")-SUMIFS(PQ_GL_Data!$I:$I,PQ_GL_Data!$C:$C,"DAL",PQ_GL_Data!$G:$G,"Revenue",PQ_GL_Data!$H:$H,"No",PQ_GL_Data!$N:$N,"2024-05") -> 50225.28 | E6: =SUM(B6:D6) -> 204221.42
A7: 2024-06 | B7: =SUMIFS(PQ_GL_Data!$J:$J,PQ_GL_Data!$C:$C,"MIA",PQ_GL_Data!$G:$G,"Revenue",PQ_GL_Data!$H:$H,"No",PQ_GL_Data!$N:$N,"2024-06")-SUMIFS(PQ_GL_Data!$I:$I,PQ_GL_Data!$C:$C,"MIA",PQ_GL_Data!$G:$G,"Revenue",PQ_GL_Data!$H:$H,"No",PQ_GL_Data!$N:$N,"2024-06") -> 103409.88 | C7: =SUMIFS(PQ_GL_Data!$J:$J,PQ_GL_Data!$C:$C,"CHI",PQ_GL_Data!$G:$G,"Revenue",PQ_GL_Data!$H:$H,"No",PQ_GL_Data!$N:$N,"2024-06")-SUMIFS(PQ_GL_Data!$I:$I,PQ_GL_Data!$C:$C,"CHI",PQ_GL_Data!$G:$G,"Revenue",PQ_GL_Data!$H:$H,"No",PQ_GL_Data!$N:$N,"2024-06") -> 57739.02 | D7: =SUMIFS(PQ_GL_Data!$J:$J,PQ_GL_Data!$C:$C,"DAL",PQ_GL_Data!$G:$G,"Revenue",PQ_GL_Data!$H:$H,"No",PQ_GL_Data!$N:$N,"2024-06")-SUMIFS(PQ_GL_Data!$I:$I,PQ_GL_Data!$C:$C,"DAL",PQ_GL_Data!$G:$G,"Revenue",PQ_GL_Data!$H:$H,"No",PQ_GL_Data!$N:$N,"2024-06") -> 54002.93 | E7: =SUM(B7:D7) -> 215151.83
A8: 2024-07 | B8: =SUMIFS(PQ_GL_Data!$J:$J,PQ_GL_Data!$C:$C,"MIA",PQ_GL_Data!$G:$G,"Revenue",PQ_GL_Data!$H:$H,"No",PQ_GL_Data!$N:$N,"2024-07")-SUMIFS(PQ_GL_Data!$I:$I,PQ_GL_Data!$C:$C,"MIA",PQ_GL_Data!$G:$G,"Revenue",PQ_GL_Data!$H:$H,"No",PQ_GL_Data!$N:$N,"2024-07") -> 100820.26 | C8: =SUMIFS(PQ_GL_Data!$J:$J,PQ_GL_Data!$C:$C,"CHI",PQ_GL_Data!$G:$G,"Revenue",PQ_GL_Data!$H:$H,"No",PQ_GL_Data!$N:$N,"2024-07")-SUMIFS(PQ_GL_Data!$I:$I,PQ_GL_Data!$C:$C,"CHI",PQ_GL_Data!$G:$G,"Revenue",PQ_GL_Data!$H:$H,"No",PQ_GL_Data!$N:$N,"2024-07") -> 57150.03 | D8: =SUMIFS(PQ_GL_Data!$J:$J,PQ_GL_Data!$C:$C,"DAL",PQ_GL_Data!$G:$G,"Revenue",PQ_GL_Data!$H:$H,"No",PQ_GL_Data!$N:$N,"2024-07")-SUMIFS(PQ_GL_Data!$I:$I,PQ_GL_Data!$C:$C,"DAL",PQ_GL_Data!$G:$G,"Revenue",PQ_GL_Data!$H:$H,"No",PQ_GL_Data!$N:$N,"2024-07") -> 53821.7 | E8: =SUM(B8:D8) -> 211791.99
A9: 2024-08 | B9: =SUMIFS(PQ_GL_Data!$J:$J,PQ_GL_Data!$C:$C,"MIA",PQ_GL_Data!$G:$G,"Revenue",PQ_GL_Data!$H:$H,"No",PQ_GL_Data!$N:$N,"2024-08")-SUMIFS(PQ_GL_Data!$I:$I,PQ_GL_Data!$C:$C,"MIA",PQ_GL_Data!$G:$G,"Revenue",PQ_GL_Data!$H:$H,"No",PQ_GL_Data!$N:$N,"2024-08") -> 91346.81 | C9: =SUMIFS(PQ_GL_Data!$J:$J,PQ_GL_Data!$C:$C,"CHI",PQ_GL_Data!$G:$G,"Revenue",PQ_GL_Data!$H:$H,"No",PQ_GL_Data!$N:$N,"2024-08")-SUMIFS(PQ_GL_Data!$I:$I,PQ_GL_Data!$C:$C,"CHI",PQ_GL_Data!$G:$G,"Revenue",PQ_GL_Data!$H:$H,"No",PQ_GL_Data!$N:$N,"2024-08") -> 66989.57 | D9: =SUMIFS(PQ_GL_Data!$J:$J,PQ_GL_Data!$C:$C,"DAL",PQ_GL_Data!$G:$G,"Revenue",PQ_GL_Data!$H:$H,"No",PQ_GL_Data!$N:$N,"2024-08")-SUMIFS(PQ_GL_Data!$I:$I,PQ_GL_Data!$C:$C,"DAL",PQ_GL_Data!$G:$G,"Revenue",PQ_GL_Data!$H:$H,"No",PQ_GL_Data!$N:$N,"2024-08") -> 50656.97 | E9: =SUM(B9:D9) -> 208993.35
A10: 2024-09 | B10: =SUMIFS(PQ_GL_Data!$J:$J,PQ_GL_Data!$C:$C,"MIA",PQ_GL_Data!$G:$G,"Revenue",PQ_GL_Data!$H:$H,"No",PQ_GL_Data!$N:$N,"2024-09")-SUMIFS(PQ_GL_Data!$I:$I,PQ_GL_Data!$C:$C,"MIA",PQ_GL_Data!$G:$G,"Revenue",PQ_GL_Data!$H:$H,"No",PQ_GL_Data!$N:$N,"2024-09") -> 100145 | C10: =SUMIFS(PQ_GL_Data!$J:$J,PQ_GL_Data!$C:$C,"CHI",PQ_GL_Data!$G:$G,"Revenue",PQ_GL_Data!$H:$H,"No",PQ_GL_Data!$N:$N,"2024-09")-SUMIFS(PQ_GL_Data!$I:$I,PQ_GL_Data!$C:$C,"CHI",PQ_GL_Data!$G:$G,"Revenue",PQ_GL_Data!$H:$H,"No",PQ_GL_Data!$N:$N,"2024-09") -> 68696.42 | D10: =SUMIFS(PQ_GL_Data!$J:$J,PQ_GL_Data!$C:$C,"DAL",PQ_GL_Data!$G:$G,"Revenue",PQ_GL_Data!$H:$H,"No",PQ_GL_Data!$N:$N,"2024-09")-SUMIFS(PQ_GL_Data!$I:$I,PQ_GL_Data!$C:$C,"DAL",PQ_GL_Data!$G:$G,"Revenue",PQ_GL_Data!$H:$H,"No",PQ_GL_Data!$N:$N,"2024-09") -> 52956.27 | E10: =SUM(B10:D10) -> 221797.69
A11: 2024-10 | B11: =SUMIFS(PQ_GL_Data!$J:$J,PQ_GL_Data!$C:$C,"MIA",PQ_GL_Data!$G:$G,"Revenue",PQ_GL_Data!$H:$H,"No",PQ_GL_Data!$N:$N,"2024-10")-SUMIFS(PQ_GL_Data!$I:$I,PQ_GL_Data!$C:$C,"MIA",PQ_GL_Data!$G:$G,"Revenue",PQ_GL_Data!$H:$H,"No",PQ_GL_Data!$N:$N,"2024-10") -> 92298.26 | C11: =SUMIFS(PQ_GL_Data!$J:$J,PQ_GL_Data!$C:$C,"CHI",PQ_GL_Data!$G:$G,"Revenue",PQ_GL_Data!$H:$H,"No",PQ_GL_Data!$N:$N,"2024-10")-SUMIFS(PQ_GL_Data!$I:$I,PQ_GL_Data!$C:$C,"CHI",PQ_GL_Data!$G:$G,"Revenue",PQ_GL_Data!$H:$H,"No",PQ_GL_Data!$N:$N,"2024-10") -> 59973.02 | D11: =SUMIFS(PQ_GL_Data!$J:$J,PQ_GL_Data!$C:$C,"DAL",PQ_GL_Data!$G:$G,"Revenue",PQ_GL_Data!$H:$H,"No",PQ_GL_Data!$N:$N,"2024-10")-SUMIFS(PQ_GL_Data!$I:$I,PQ_GL_Data!$C:$C,"DAL",PQ_GL_Data!$G:$G,"Revenue",PQ_GL_Data!$H:$H,"No",PQ_GL_Data!$N:$N,"2024-10") -> 58370.52 | E11: =SUM(B11:D11) -> 210641.8
A12: 2024-11 | B12: =SUMIFS(PQ_GL_Data!$J:$J,PQ_GL_Data!$C:$C,"MIA",PQ_GL_Data!$G:$G,"Revenue",PQ_GL_Data!$H:$H,"No",PQ_GL_Data!$N:$N,"2024-11")-SUMIFS(PQ_GL_Data!$I:$I,PQ_GL_Data!$C:$C,"MIA",PQ_GL_Data!$G:$G,"Revenue",PQ_GL_Data!$H:$H,"No",PQ_GL_Data!$N:$N,"2024-11") -> 109251.24 | C12: =SUMIFS(PQ_GL_Data!$J:$J,PQ_GL_Data!$C:$C,"CHI",PQ_GL_Data!$G:$G,"Revenue",PQ_GL_Data!$H:$H,"No",PQ_GL_Data!$N:$N,"2024-11")-SUMIFS(PQ_GL_Data!$I:$I,PQ_GL_Data!$C:$C,"CHI",PQ_GL_Data!$G:$G,"Revenue",PQ_GL_Data!$H:$H,"No",PQ_GL_Data!$N:$N,"2024-11") -> 67924.17 | D12: =SUMIFS(PQ_GL_Data!$J:$J,PQ_GL_Data!$C:$C,"DAL",PQ_GL_Data!$G:$G,"Revenue",PQ_GL_Data!$H:$H,"No",PQ_GL_Data!$N:$N,"2024-11")-SUMIFS(PQ_GL_Data!$I:$I,PQ_GL_Data!$C:$C,"DAL",PQ_GL_Data!$G:$G,"Revenue",PQ_GL_Data!$H:$H,"No",PQ_GL_Data!$N:$N,"2024-11") -> 56021.86 | E12: =SUM(B12:D12) -> 233197.27
A13: 2024-12 | B13: =SUMIFS(PQ_GL_Data!$J:$J,PQ_GL_Data!$C:$C,"MIA",PQ_GL_Data!$G:$G,"Revenue",PQ_GL_Data!$H:$H,"No",PQ_GL_Data!$N:$N,"2024-12")-SUMIFS(PQ_GL_Data!$I:$I,PQ_GL_Data!$C:$C,"MIA",PQ_GL_Data!$G:$G,"Revenue",PQ_GL_Data!$H:$H,"No",PQ_GL_Data!$N:$N,"2024-12") -> 103579.06 | C13: =SUMIFS(PQ_GL_Data!$J:$J,PQ_GL_Data!$C:$C,"CHI",PQ_GL_Data!$G:$G,"Revenue",PQ_GL_Data!$H:$H,"No",PQ_GL_Data!$N:$N,"2024-12")-SUMIFS(PQ_GL_Data!$I:$I,PQ_GL_Data!$C:$C,"CHI",PQ_GL_Data!$G:$G,"Revenue",PQ_GL_Data!$H:$H,"No",PQ_GL_Data!$N:$N,"2024-12") -> 67103.43 | D13: =SUMIFS(PQ_GL_Data!$J:$J,PQ_GL_Data!$C:$C,"DAL",PQ_GL_Data!$G:$G,"Revenue",PQ_GL_Data!$H:$H,"No",PQ_GL_Data!$N:$N,"2024-12")-SUMIFS(PQ_GL_Data!$I:$I,PQ_GL_Data!$C:$C,"DAL",PQ_GL_Data!$G:$G,"Revenue",PQ_GL_Data!$H:$H,"No",PQ_GL_Data!$N:$N,"2024-12") -> 56773.83 | E13: =SUM(B13:D13) -> 227456.32
A14: 2025-01 | B14: =SUMIFS(PQ_GL_Data!$J:$J,PQ_GL_Data!$C:$C,"MIA",PQ_GL_Data!$G:$G,"Revenue",PQ_GL_Data!$H:$H,"No",PQ_GL_Data!$N:$N,"2025-01")-SUMIFS(PQ_GL_Data!$I:$I,PQ_GL_Data!$C:$C,"MIA",PQ_GL_Data!$G:$G,"Revenue",PQ_GL_Data!$H:$H,"No",PQ_GL_Data!$N:$N,"2025-01") -> 98795.78 | C14: =SUMIFS(PQ_GL_Data!$J:$J,PQ_GL_Data!$C:$C,"CHI",PQ_GL_Data!$G:$G,"Revenue",PQ_GL_Data!$H:$H,"No",PQ_GL_Data!$N:$N,"2025-01")-SUMIFS(PQ_GL_Data!$I:$I,PQ_GL_Data!$C:$C,"CHI",PQ_GL_Data!$G:$G,"Revenue",PQ_GL_Data!$H:$H,"No",PQ_GL_Data!$N:$N,"2025-01") -> 71525.54 | D14: =SUMIFS(PQ_GL_Data!$J:$J,PQ_GL_Data!$C:$C,"DAL",PQ_GL_Data!$G:$G,"Revenue",PQ_GL_Data!$H:$H,"No",PQ_GL_Data!$N:$N,"2025-01")-SUMIFS(PQ_GL_Data!$I:$I,PQ_GL_Data!$C:$C,"DAL",PQ_GL_Data!$G:$G,"Revenue",PQ_GL_Data!$H:$H,"No",PQ_GL_Data!$N:$N,"2025-01") -> 61850.4 | E14: =SUM(B14:D14) -> 232171.72
A15: 2025-02 | B15: =SUMIFS(PQ_GL_Data!$J:$J,PQ_GL_Data!$C:$C,"MIA",PQ_GL_Data!$G:$G,"Revenue",PQ_GL_Data!$H:$H,"No",PQ_GL_Data!$N:$N,"2025-02")-SUMIFS(PQ_GL_Data!$I:$I,PQ_GL_Data!$C:$C,"MIA",PQ_GL_Data!$G:$G,"Revenue",PQ_GL_Data!$H:$H,"No",PQ_GL_Data!$N:$N,"2025-02") -> 112245.2 | C15: =SUMIFS(PQ_GL_Data!$J:$J,PQ_GL_Data!$C:$C,"CHI",PQ_GL_Data!$G:$G,"Revenue",PQ_GL_Data!$H:$H,"No",PQ_GL_Data!$N:$N,"2025-02")-SUMIFS(PQ_GL_Data!$I:$I,PQ_GL_Data!$C:$C,"CHI",PQ_GL_Data!$G:$G,"Revenue",PQ_GL_Data!$H:$H,"No",PQ_GL_Data!$N:$N,"2025-02") -> 64862.38 | D15: =SUMIFS(PQ_GL_Data!$J:$J,PQ_GL_Data!$C:$C,"DAL",PQ_GL_Data!$G:$G,"Revenue",PQ_GL_Data!$H:$H,"No",PQ_GL_Data!$N:$N,"2025-02")-SUMIFS(PQ_GL_Data!$I:$I,PQ_GL_Data!$C:$C,"DAL",PQ_GL_Data!$G:$G,"Revenue",PQ_GL_Data!$H:$H,"No",PQ_GL_Data!$N:$N,"2025-02") -> 58252.84 | E15: =SUM(B15:D15) -> 235360.42
A16: 2025-03 | B16: =SUMIFS(PQ_GL_Data!$J:$J,PQ_GL_Data!$C:$C,"MIA",PQ_GL_Data!$G:$G,"Revenue",PQ_GL_Data!$H:$H,"No",PQ_GL_Data!$N:$N,"2025-03")-SUMIFS(PQ_GL_Data!$I:$I,PQ_GL_Data!$C:$C,"MIA",PQ_GL_Data!$G:$G,"Revenue",PQ_GL_Data!$H:$H,"No",PQ_GL_Data!$N:$N,"2025-03") -> 97351.1 | C16: =SUMIFS(PQ_GL_Data!$J:$J,PQ_GL_Data!$C:$C,"CHI",PQ_GL_Data!$G:$G,"Revenue",PQ_GL_Data!$H:$H,"No",PQ_GL_Data!$N:$N,"2025-03")-SUMIFS(PQ_GL_Data!$I:$I,PQ_GL_Data!$C:$C,"CHI",PQ_GL_Data!$G:$G,"Revenue",PQ_GL_Data!$H:$H,"No",PQ_GL_Data!$N:$N,"2025-03") -> 63657.99 | D16: =SUMIFS(PQ_GL_Data!$J:$J,PQ_GL_Data!$C:$C,"DAL",PQ_GL_Data!$G:$G,"Revenue",PQ_GL_Data!$H:$H,"No",PQ_GL_Data!$N:$N,"2025-03")-SUMIFS(PQ_GL_Data!$I:$I,PQ_GL_Data!$C:$C,"DAL",PQ_GL_Data!$G:$G,"Revenue",PQ_GL_Data!$H:$H,"No",PQ_GL_Data!$N:$N,"2025-03") -> 53455.7 | E16: =SUM(B16:D16) -> 214464.79
A17: 2025-04 | B17: =SUMIFS(PQ_GL_Data!$J:$J,PQ_GL_Data!$C:$C,"MIA",PQ_GL_Data!$G:$G,"Revenue",PQ_GL_Data!$H:$H,"No",PQ_GL_Data!$N:$N,"2025-04")-SUMIFS(PQ_GL_Data!$I:$I,PQ_GL_Data!$C:$C,"MIA",PQ_GL_Data!$G:$G,"Revenue",PQ_GL_Data!$H:$H,"No",PQ_GL_Data!$N:$N,"2025-04") -> 117271.53 | C17: =SUMIFS(PQ_GL_Data!$J:$J,PQ_GL_Data!$C:$C,"CHI",PQ_GL_Data!$G:$G,"Revenue",PQ_GL_Data!$H:$H,"No",PQ_GL_Data!$N:$N,"2025-04")-SUMIFS(PQ_GL_Data!$I:$I,PQ_GL_Data!$C:$C,"CHI",PQ_GL_Data!$G:$G,"Revenue",PQ_GL_Data!$H:$H,"No",PQ_GL_Data!$N:$N,"2025-04") -> 62085.39 | D17: =SUMIFS(PQ_GL_Data!$J:$J,PQ_GL_Data!$C:$C,"DAL",PQ_GL_Data!$G:$G,"Revenue",PQ_GL_Data!$H:$H,"No",PQ_GL_Data!$N:$N,"2025-04")-SUMIFS(PQ_GL_Data!$I:$I,PQ_GL_Data!$C:$C,"DAL",PQ_GL_Data!$G:$G,"Revenue",PQ_GL_Data!$H:$H,"No",PQ_GL_Data!$N:$N,"2025-04") -> 64897.02 | E17: =SUM(B17:D17) -> 244253.94
A18: 2025-05 | B18: =SUMIFS(PQ_GL_Data!$J:$J,PQ_GL_Data!$C:$C,"MIA",PQ_GL_Data!$G:$G,"Revenue",PQ_GL_Data!$H:$H,"No",PQ_GL_Data!$N:$N,"2025-05")-SUMIFS(PQ_GL_Data!$I:$I,PQ_GL_Data!$C:$C,"MIA",PQ_GL_Data!$G:$G,"Revenue",PQ_GL_Data!$H:$H,"No",PQ_GL_Data!$N:$N,"2025-05") -> 111681.6 | C18: =SUMIFS(PQ_GL_Data!$J:$J,PQ_GL_Data!$C:$C,"CHI",PQ_GL_Data!$G:$G,"Revenue",PQ_GL_Data!$H:$H,"No",PQ_GL_Data!$N:$N,"2025-05")-SUMIFS(PQ_GL_Data!$I:$I,PQ_GL_Data!$C:$C,"CHI",PQ_GL_Data!$G:$G,"Revenue",PQ_GL_Data!$H:$H,"No",PQ_GL_Data!$N:$N,"2025-05") -> 66861.5 | D18: =SUMIFS(PQ_GL_Data!$J:$J,PQ_GL_Data!$C:$C,"DAL",PQ_GL_Data!$G:$G,"Revenue",PQ_GL_Data!$H:$H,"No",PQ_GL_Data!$N:$N,"2025-05")-SUMIFS(PQ_GL_Data!$I:$I,PQ_GL_Data!$C:$C,"DAL",PQ_GL_Data!$G:$G,"Revenue",PQ_GL_Data!$H:$H,"No",PQ_GL_Data!$N:$N,"2025-05") -> 55419.71 | E18: =SUM(B18:D18) -> 233962.81
A19: 2025-06 | B19: =SUMIFS(PQ_GL_Data!$J:$J,PQ_GL_Data!$C:$C,"MIA",PQ_GL_Data!$G:$G,"Revenue",PQ_GL_Data!$H:$H,"No",PQ_GL_Data!$N:$N,"2025-06")-SUMIFS(PQ_GL_Data!$I:$I,PQ_GL_Data!$C:$C,"MIA",PQ_GL_Data!$G:$G,"Revenue",PQ_GL_Data!$H:$H,"No",PQ_GL_Data!$N:$N,"2025-06") -> 113863.1 | C19: =SUMIFS(PQ_GL_Data!$J:$J,PQ_GL_Data!$C:$C,"CHI",PQ_GL_Data!$G:$G,"Revenue",PQ_GL_Data!$H:$H,"No",PQ_GL_Data!$N:$N,"2025-06")-SUMIFS(PQ_GL_Data!$I:$I,PQ_GL_Data!$C:$C,"CHI",PQ_GL_Data!$G:$G,"Revenue",PQ_GL_Data!$H:$H,"No",PQ_GL_Data!$N:$N,"2025-06") -> 69904.78 | D19: =SUMIFS(PQ_GL_Data!$J:$J,PQ_GL_Data!$C:$C,"DAL",PQ_GL_Data!$G:$G,"Revenue",PQ_GL_Data!$H:$H,"No",PQ_GL_Data!$N:$N,"2025-06")-SUMIFS(PQ_GL_Data!$I:$I,PQ_GL_Data!$C:$C,"DAL",PQ_GL_Data!$G:$G,"Revenue",PQ_GL_Data!$H:$H,"No",PQ_GL_Data!$N:$N,"2025-06") -> 57235.2 | E19: =SUM(B19:D19) -> 241003.08
A22: Entity | B22: Total Budget (COGS+Opex) | C22: Total Actual (COGS+Opex)
A23: MIA | B23: =SUMIFS(Budget_vs_Actual!$C:$C,Budget_vs_Actual!$A:$A,"MIA") -> 182255.35 | C23: =SUMIFS(Budget_vs_Actual!$D:$D,Budget_vs_Actual!$A:$A,"MIA") -> 185812.48
A24: CHI | B24: =SUMIFS(Budget_vs_Actual!$C:$C,Budget_vs_Actual!$A:$A,"CHI") -> 116491.22 | C24: =SUMIFS(Budget_vs_Actual!$D:$D,Budget_vs_Actual!$A:$A,"CHI") -> 118265.53
A25: DAL | B25: =SUMIFS(Budget_vs_Actual!$C:$C,Budget_vs_Actual!$A:$A,"DAL") -> 97555.94 | C25: =SUMIFS(Budget_vs_Actual!$D:$D,Budget_vs_Actual!$A:$A,"DAL") -> 99997.86

Sheet PQ_GL_Data
A1: TxnID | B1: JournalID | C1: EntityCode | D1: Date | E1: AccountCode | F1: AccountName | G1: AccountType | H1: IsIntercompany | I1: Debit | J1: Credit | K1: Description | L1: Source | M1: CounterpartyEntity | N1: MonthKey
A2: 1 | B2: 1 | C2: MIA | D2: 2024-01-12 | E2: 1100 | F2: Accounts Receivable | G2: Asset | H2: No | I2: 95742 | J2: 0 | K2: MIA legal fees billed - 2024-01 | L2: Billing | N2: 2024-01
A3: 2 | B3: 1 | C3: MIA | D3: 2024-01-12 | E3: 4010 | F3: Litigation Fees | G3: Revenue | H3: No | I3: 0 | J3: 40211.64 | K3: MIA legal fees billed - 2024-01 | L3: Billing | N3: 2024-01
A4: 3 | B4: 1 | C4: MIA | D4: 2024-01-12 | E4: 4020 | F4: Corporate & Transactional Fees | G4: Revenue | H4: No | I4: 0 | J4: 31594.86 | K4: MIA legal fees billed - 2024-01 | L4: Billing | N4: 2024-01
A5: 4 | B5: 1 | C5: MIA | D5: 2024-01-12 | E5: 4030 | F5: Family Law Fees | G5: Revenue | H5: No | I5: 0 | J5: 23935.5 | K5: MIA legal fees billed - 2024-01 | L5: Billing | N5: 2024-01
A6: 5 | B6: 2 | C6: MIA | D6: 2024-01-24 | E6: 1000 | F6: Cash - Operating | G6: Asset | H6: No | I6: 89893.86 | J6: 0 | K6: MIA client fee collections - 2024-01 | L6: Cash Receipt | N6: 2024-01
A7: 6 | B7: 2 | C7: MIA | D7: 2024-01-24 | E7: 1100 | F7: Accounts Receivable | G7: Asset | H7: No | I7: 0 | J7: 89893.86 | K7: MIA client fee collections - 2024-01 | L7: Cash Receipt | N7: 2024-01
A8: 7 | B8: 3 | C8: MIA | D8: 2024-01-15 | E8: 5010 | F8: Court Filing Fees | G8: COGS | H8: No | I8: 5437.52 | J8: 0 | K8: MIA direct case costs - 2024-01 | L8: AP/Cash | N8: 2024-01
A9: 8 | B9: 3 | C9: MIA | D9: 2024-01-15 | E9: 5020 | F9: Expert Witness Fees | G9: COGS | H9: No | I9: 4448.88 | J9: 0 | K9: MIA direct case costs - 2024-01 | L9: AP/Cash | N9: 2024-01
A10: 9 | B10: 3 | C10: MIA | D10: 2024-01-15 | E10: 1000 | F10: Cash - Operating | G10: Asset | H10: No | I10: 0 | J10: 6920.48 | K10: MIA direct case costs - 2024-01 | L10: AP/Cash | N10: 2024-01
A11: 10 | B11: 3 | C11: MIA | D11: 2024-01-15 | E11: 2000 | F11: Accounts Payable | G11: Liability | H11: No | I11: 0 | J11: 2965.92 | K11: MIA direct case costs - 2024-01 | L11: AP/Cash | N11: 2024-01
A12: 11 | B12: 4 | C12: MIA | D12: 2024-01-29 | E12: 6010 | F12: Attorney & Staff Payroll | G12: Opex | H12: No | I12: 41000 | J12: 0 | K12: MIA payroll run - 2024-01 | L12: Payroll | N12: 2024-01
A13: 12 | B13: 4 | C13: MIA | D13: 2024-01-29 | E13: 6020 | F13: Payroll Taxes & Benefits | G13: Opex | H13: No | I13: 5740 | J13: 0 | K13: MIA payroll run - 2024-01 | L13: Payroll | N13: 2024-01
... A79: 78 | B79: 27 | C79: DAL | D79: 2024-01-31 | E79: 1500 | F79: Fixed Assets, Net | G79: Asset | H79: No | I79: 0 | J79: 605 | K79: DAL monthly depreciation - 2024-01 | L79: Adjusting Entry | N79: 2024-01
A80: 79 | B80: 28 | C80: MIA | D80: 2024-01-22 | E80: 1300 | F80: Intercompany Receivable | G80: Asset | H80: Yes | I80: 3224 | J80: 0 | K80: Shared services billed to branch 2 - 2024-01 | L80: Intercompany | M80: CHI | N80: 2024-01
A81: 80 | B81: 28 | C81: MIA | D81: 2024-01-22 | E81: 4090 | F81: Intercompany Shared Services Revenue | G81: Revenue | H81: Yes | I81: 0 | J81: 3224 | K81: Shared services billed to branch 2 - 2024-01 | L81: Intercompany | M81: CHI | N81: 2024-01
A82: 81 | B82: 29 | C82: CHI | D82: 2024-01-22 | E82: 6070 | F82: Shared Services Allocation (Intercompany) | G82: Opex | H82: Yes | I82: 3224 | J82: 0 | K82: Shared services allocation from HQ - 2024-01 | L82: Intercompany | M82: MIA | N82: 2024-01
A83: 82 | B83: 29 | C83: CHI | D83: 2024-01-22 | E83: 2200 | F83: Intercompany Payable | G83: Liability | H83: Yes | I83: 0 | J83: 3224 | K83: Shared services allocation from HQ - 2024-01 | L83: Intercompany | M83: MIA | N83: 2024-01
A84: 83 | B84: 30 | C84: MIA | D84: 2024-01-22 | E84: 1300 | F84: Intercompany Receivable | G84: Asset | H84: Yes | I84: 2860 | J84: 0 | K84: Shared services billed to branch 3 - 2024-01 | L84: Intercompany | M84: DAL | N84: 2024-01
A85: 84 | B85: 30 | C85: MIA | D85: 2024-01-22 | E85: 4090 | F85: Intercompany Shared Services Revenue | G85: Revenue | H85: Yes | I85: 0 | J85: 2860 | K85: Shared services billed to branch 3 - 2024-01 | L85: Intercompany | M85: DAL | N85: 2024-01
A86: 85 | B86: 31 | C86: DAL | D86: 2024-01-22 | E86: 6070 | F86: Shared Services Allocation (Intercompany) | G86: Opex | H86: Yes | I86: 2860 | J86: 0 | K86: Shared services allocation from HQ - 2024-01 | L86: Intercompany | M86: MIA | N86: 2024-01
A87: 86 | B87: 31 | C87: DAL | D87: 2024-01-22 | E87: 2200 | F87: Intercompany Payable | G87: Liability | H87: Yes | I87: 0 | J87: 2860 | K87: Shared services allocation from HQ - 2024-01 | L87: Intercompany | M87: MIA | N87: 2024-01
A88: 87 | B88: 32 | C88: MIA | D88: 2024-02-12 | E88: 1100 | F88: Accounts Receivable | G88: Asset | H88: No | I88: 100782.2 | J88: 0 | K88: MIA legal fees billed - 2024-02 | L88: Billing | N88: 2024-02
A89: 88 | B89: 32 | C89: MIA | D89: 2024-02-12 | E89: 4010 | F89: Litigation Fees | G89: Revenue | H89: No | I89: 0 | J89: 42328.52 | K89: MIA legal fees billed - 2024-02 | L89: Billing | N89: 2024-02
A90: 89 | B90: 32 | C90: MIA | D90: 2024-02-12 | E90: 4020 | F90: Corporate & Transactional Fees | G90: Revenue | H90: No | I90: 0 | J90: 33258.13 | K90: MIA legal fees billed - 2024-02 | L90: Billing | N90: 2024-02
A91: 90 | B91: 32 | C91: MIA | D91: 2024-02-12 | E91: 4030 | F91: Family Law Fees | G91: Revenue | H91: No | I91: 0 | J91: 25195.55 | K91: MIA legal fees billed - 2024-02 | L91: Billing | N91: 2024-02
A92: 91 | B92: 33 | C92: MIA | D92: 2024-02-26 | E92: 1000 | F92: Cash - Operating | G92: Asset | H92: No | I92: 94369 | J92: 0 | K92: MIA client fee collections - 2024-02 | L92: Cash Receipt | N92: 2024-02
A93: 92 | B93: 33 | C93: MIA | D93: 2024-02-26 | E93: 1100 | F93: Accounts Receivable | G93: Asset | H93: No | I93: 0 | J93: 94369 | K93: MIA client fee collections - 2024-02 | L93: Cash Receipt | N93: 2024-02
A94: 93 | B94: 34 | C94: MIA | D94: 2024-02-15 | E94: 5010 | F94: Court Filing Fees | G94: COGS | H94: No | I94: 5723.77 | J94: 0 | K94: MIA direct case costs - 2024-02 | L94: AP/Cash | N94: 2024-02
A95: 94 | B95: 34 | C95: MIA | D95: 2024-02-15 | E95: 5020 | F95: Expert Witness Fees | G95: COGS | H95: No | I95: 4683.09 | J95: 0 | K95: MIA direct case costs - 2024-02 | L95: AP/Cash | N95: 2024-02
A96: 95 | B96: 34 | C96: MIA | D96: 2024-02-15 | E96: 1000 | F96: Cash - Operating | G96: Asset | H96: No | I96: 0 | J96: 7284.8 | K96: MIA direct case costs - 2024-02 | L96: AP/Cash | N96: 2024-02
A97: 96 | B97: 34 | C97: MIA | D97: 2024-02-15 | E97: 2000 | F97: Accounts Payable | G97: Liability | H97: No | I97: 0 | J97: 3122.06 | K97: MIA direct case costs - 2024-02 | L97: AP/Cash | N97: 2024-02
A98: 97 | B98: 35 | C98: MIA | D98: 2024-02-28 | E98: 6010 | F98: Attorney & Staff Payroll | G98: Opex | H98: No | I98: 41492 | J98: 0 | K98: MIA payroll run - 2024-02 | L98: Payroll | N98: 2024-02
A99: 98 | B99: 35 | C99: MIA | D99: 2024-02-28 | E99: 6020 | F99: Payroll Taxes & Benefits | G99: Opex | H99: No | I99: 5808.88 | J99: 0 | K99: MIA payroll run - 2024-02 | L99: Payroll | N99: 2024-02
... A171: 170 | B171: 61 | C171: DAL | D171: 2024-02-05 | E171: 1000 | F171: Cash - Operating | G171: Asset | H171: No | I171: 0 | J171: 2131.78 | K171: DAL AP payment run (prior month invoices) - 2024-02 | L171: Cash | N171: 2024-02
A172: 171 | B172: 62 | C172: MIA | D172: 2024-02-20 | E172: 1300 | F172: Intercompany Receivable | G172: Asset | H172: Yes | I172: 3256.24 | J172: 0 | K172: Shared services billed to branch 2 - 2024-02 | L172: Intercompany | M172: CHI | N172: 2024-02
A173: 172 | B173: 62 | C173: MIA | D173: 2024-02-20 | E173: 4090 | F173: Intercompany Shared Services Revenue | G173: Revenue | H173: Yes | I173: 0 | J173: 3256.24 | K173: Shared services billed to branch 2 - 2024-02 | L173: Intercompany | M173: CHI | N173: 2024-02
A174: 173 | B174: 63 | C174: CHI | D174: 2024-02-20 | E174: 6070 | F174: Shared Services Allocation (Intercompany) | G174: Opex | H174: Yes | I174: 3256.24 | J174: 0 | K174: Shared services allocation from HQ - 2024-02 | L174: Intercompany | M174: MIA | N174: 2024-02
A175: 174 | B175: 63 | C175: CHI | D175: 2024-02-20 | E175: 2200 | F175: Intercompany Payable | G175: Liability | H175: Yes | I175: 0 | J175: 3256.24 | K175: Shared services allocation from HQ - 2024-02 | L175: Intercompany | M175: MIA | N175: 2024-02
A176: 175 | B176: 64 | C176: CHI | D176: 2024-02-26 | E176: 2200 | F176: Intercompany Payable | G176: Liability | H176: Yes | I176: 3224 | J176: 0 | K176: Intercompany settlement paid to HQ - 2024-02 | L176: Intercompany Cash | M176: MIA | N176: 2024-02
A177: 176 | B177: 64 | C177: CHI | D177: 2024-02-26 | E177: 1000 | F177: Cash - Operating | G177: Asset | H177: No | I177: 0 | J177: 3224 | K177: Intercompany settlement paid to HQ - 2024-02 | L177: Intercompany Cash | M177: MIA | N177: 2024-02
A178: 177 | B178: 65 | C178: MIA | D178: 2024-02-26 | E178: 1000 | F178: Cash - Operating | G178: Asset | H178: No | I178: 3224 | J178: 0 | K178: Intercompany settlement received from branch 2 - 2024-02 | L178: Intercompany Cash | M178: CHI | N178: 2024-02
A179: 178 | B179: 65 | C179: MIA | D179: 2024-02-26 | E179: 1300 | F179: Intercompany Receivable | G179: Asset | H179: Yes | I179: 0 | J179: 3224 | K179: Intercompany settlement received from branch 2 - 2024-02 | L179: Intercompany Cash | M179: CHI | N179: 2024-02
A180: 179 | B180: 66 | C180: MIA | D180: 2024-02-20 | E180: 1300 | F180: Intercompany Receivable | G180: Asset | H180: Yes | I180: 2888.6 | J180: 0 | K180: Shared services billed to branch 3 - 2024-02 | L180: Intercompany | M180: DAL | N180: 2024-02
A181: 180 | B181: 66 | C181: MIA | D181: 2024-02-20 | E181: 4090 | F181: Intercompany Shared Services Revenue | G181: Revenue | H181: Yes | I181: 0 | J181: 2888.6 | K181: Shared services billed to branch 3 - 2024-02 | L181: Intercompany | M181: DAL | N181: 2024-02
A182: 181 | B182: 67 | C182: DAL | D182: 2024-02-20 | E182: 6070 | F182: Shared Services Allocation (Intercompany) | G182: Opex | H182: Yes | I182: 2888.6 | J182: 0 | K182: Shared services allocation from HQ - 2024-02 | L182: Intercompany | M182: MIA | N182: 2024-02
A183: 182 | B183: 67 | C183: DAL | D183: 2024-02-20 | E183: 2200 | F183: Intercompany Payable | G183: Liability | H183: Yes | I183: 0 | J183: 2888.6 | K183: Shared services allocation from HQ - 2024-02 | L183: Intercompany | M183: MIA | N183: 2024-02
... A187: 186 | B187: 69 | C187: MIA | D187: 2024-02-26 | E187: 1300 | F187: Intercompany Receivable | G187: Asset | H187: Yes | I187: 0 | J187: 2860 | K187: Intercompany settlement received from branch 3 - 2024-02 | L187: Intercompany Cash | M187: DAL | N187: 2024-02
A188: 187 | B188: 70 | C188: MIA | D188: 2024-03-12 | E188: 1100 | F188: Accounts Receivable | G188: Asset | H188: No | I188: 102950.59 | J188: 0 | K188: MIA legal fees billed - 2024-03 | L188: Billing | N188: 2024-03
A189: 188 | B189: 70 | C189: MIA | D189: 2024-03-12 | E189: 4010 | F189: Litigation Fees | G189: Revenue | H189: No | I189: 0 | J189: 43239.25 | K189: MIA legal fees billed - 2024-03 | L189: Billing | N189: 2024-03
A190: 189 | B190: 70 | C190: MIA | D190: 2024-03-12 | E190: 4020 | F190: Corporate & Transactional Fees | G190: Revenue | H190: No | I190: 0 | J190: 33973.69 | K190: MIA legal fees billed - 2024-03 | L190: Billing | N190: 2024-03
A191: 190 | B191: 70 | C191: MIA | D191: 2024-03-12 | E191: 4030 | F191: Family Law Fees | G191: Revenue | H191: No | I191: 0 | J191: 25737.65 | K191: MIA legal fees billed - 2024-03 | L191: Billing | N191: 2024-03
A192: 191 | B192: 71 | C192: MIA | D192: 2024-03-25 | E192: 1000 | F192: Cash - Operating | G192: Asset | H192: No | I192: 98128.78 | J192: 0 | K192: MIA client fee collections - 2024-03 | L192: Cash Receipt | N192: 2024-03
A193: 192 | B193: 71 | C193: MIA | D193: 2024-03-25 | E193: 1100 | F193: Accounts Receivable | G193: Asset | H193: No | I193: 0 | J193: 98128.78 | K193: MIA client fee collections - 2024-03 | L193: Cash Receipt | N193: 2024-03
A194: 193 | B194: 72 | C194: MIA | D194: 2024-03-15 | E194: 5010 | F194: Court Filing Fees | G194: COGS | H194: No | I194: 5846.92 | J194: 0 | K194: MIA direct case costs - 2024-03 | L194: AP/Cash | N194: 2024-03
A195: 194 | B195: 72 | C195: MIA | D195: 2024-03-15 | E195: 5020 | F195: Expert Witness Fees | G195: COGS | H195: No | I195: 4783.85 | J195: 0 | K195: MIA direct case costs - 2024-03 | L195: AP/Cash | N195: 2024-03
A196: 195 | B196: 72 | C196: MIA | D196: 2024-03-15 | E196: 1000 | F196: Cash - Operating | G196: Asset | H196: No | I196: 0 | J196: 7441.54 | K196: MIA direct case costs - 2024-03 | L196: AP/Cash | N196: 2024-03
A197: 196 | B197: 72 | C197: MIA | D197: 2024-03-15 | E197: 2000 | F197: Accounts Payable | G197: Liability | H197: No | I197: 0 | J197: 3189.23 | K197: MIA direct case costs - 2024-03 | L197: AP/Cash | N197: 2024-03
A198: 197 | B198: 73 | C198: MIA | D198: 2024-03-28 | E198: 6010 | F198: Attorney & Staff Payroll | G198: Opex | H198: No | I198: 41984 | J198: 0 | K198: MIA payroll run - 2024-03 | L198: Payroll | N198: 2024-03
A199: 198 | B199: 73 | C199: MIA | D199: 2024-03-28 | E199: 6020 | F199: Payroll Taxes & Benefits | G199: Opex | H199: No | I199: 5877.76 | J199: 0 | K199: MIA payroll run - 2024-03 | L199: Payroll | N199: 2024-03
... A271: 270 | B271: 99 | C271: DAL | D271: 2024-03-05 | E271: 1000 | F271: Cash - Operating | G271: Asset | H271: No | I271: 0 | J271: 2166.44 | K271: DAL AP payment run (prior month invoices) - 2024-03 | L271: Cash | N271: 2024-03
A272: 271 | B272: 100 | C272: MIA | D272: 2024-03-20 | E272: 1300 | F272: Intercompany Receivable | G272: Asset | H272: Yes | I272: 3288.48 | J272: 0 | K272: Shared services billed to branch 2 - 2024-03 | L272: Intercompany | M272: CHI | N272: 2024-03
A273: 272 | B273: 100 | C273: MIA | D273: 2024-03-20 | E273: 4090 | F273: Intercompany Shared Services Revenue | G273: Revenue | H273: Yes | I273: 0 | J273: 3288.48 | K273: Shared services billed to branch 2 - 2024-03 | L273: Intercompany | M273: CHI | N273: 2024-03
A274: 273 | B274: 101 | C274: CHI | D274: 2024-03-20 | E274: 6070 | F274: Shared Services Allocation (Intercompany) | G274: Opex | H274: Yes | I274: 3288.48 | J274: 0 | K274: Shared services allocation from HQ - 2024-03 | L274: Intercompany | M274: MIA | N274: 2024-03
A275: 274 | B275: 101 | C275: CHI | D275: 2024-03-20 | E275: 2200 | F275: Intercompany Payable | G275: Liability | H275: Yes | I275: 0 | J275: 3288.48 | K275: Shared services allocation from HQ - 2024-03 | L275: Intercompany | M275: MIA | N275: 2024-03
A276: 275 | B276: 102 | C276: CHI | D276: 2024-03-25 | E276: 2200 | F276: Intercompany Payable | G276: Liability | H276: Yes | I276: 3256.24 | J276: 0 | K276: Intercompany settlement paid to HQ - 2024-03 | L276: Intercompany Cash | M276: MIA | N276: 2024-03
A277: 276 | B277: 102 | C277: CHI | D277: 2024-03-25 | E277: 1000 | F277: Cash - Operating | G277: Asset | H277: No | I277: 0 | J277: 3256.24 | K277: Intercompany settlement paid to HQ - 2024-03 | L277: Intercompany Cash | M277: MIA | N277: 2024-03
A278: 277 | B278: 103 | C278: MIA | D278: 2024-03-25 | E278: 1000 | F278: Cash - Operating | G278: Asset | H278: No | I278: 3256.24 | J278: 0 | K278: Intercompany settlement received from branch 2 - 2024-03 | L278: Intercompany Cash | M278: CHI | N278: 2024-03
A279: 278 | B279: 103 | C279: MIA | D279: 2024-03-25 | E279: 1300 | F279: Intercompany Receivable | G279: Asset | H279: Yes | I279: 0 | J279: 3256.24 | K279: Intercompany settlement received from branch 2 - 2024-03 | L279: Intercompany Cash | M279: CHI | N279: 2024-03
A280: 279 | B280: 104 | C280: MIA | D280: 2024-03-20 | E280: 1300 | F280: Intercompany Receivable | G280: Asset | H280: Yes | I280: 2917.2 | J280: 0 | K280: Shared services billed to branch 3 - 2024-03 | L280: Intercompany | M280: DAL | N280: 2024-03
A281: 280 | B281: 104 | C281: MIA | D281: 2024-03-20 | E281: 4090 | F281: Intercompany Shared Services Revenue | G281: Revenue | H281: Yes | I281: 0 | J281: 2917.2 | K281: Shared services billed to branch 3 - 2024-03 | L281: Intercompany | M281: DAL | N281: 2024-03
A282: 281 | B282: 105 | C282: DAL | D282: 2024-03-20 | E282: 6070 | F282: Shared Services Allocation (Intercompany) | G282: Opex | H282: Yes | I282: 2917.2 | J282: 0 | K282: Shared services allocation from HQ - 2024-03 | L282: Intercompany | M282: MIA | N282: 2024-03
A283: 282 | B283: 105 | C283: DAL | D283: 2024-03-20 | E283: 2200 | F283: Intercompany Payable | G283: Liability | H283: Yes | I283: 0 | J283: 2917.2 | K283: Shared services allocation from HQ - 2024-03 | L283: Intercompany | M283: MIA | N283: 2024-03
... A287: 286 | B287: 107 | C287: MIA | D287: 2024-03-25 | E287: 1300 | F287: Intercompany Receivable | G287: Asset | H287: Yes | I287: 0 | J287: 2888.6 | K287: Intercompany settlement received from branch 3 - 2024-03 | L287: Intercompany Cash | M287: DAL | N287: 2024-03
A288: 287 | B288: 108 | C288: MIA | D288: 2024-04-12 | E288: 1100 | F288: Accounts Receivable | G288: Asset | H288: No | I288: 95294.77 | J288: 0 | K288: MIA legal fees billed - 2024-04 | L288: Billing | N288: 2024-04
A289: 288 | B289: 108 | C289: MIA | D289: 2024-04-12 | E289: 4010 | F289: Litigation Fees | G289: Revenue | H289: No | I289: 0 | J289: 40023.8 | K289: MIA legal fees billed - 2024-04 | L289: Billing | N289: 2024-04
A290: 289 | B290: 108 | C290: MIA | D290: 2024-04-12 | E290: 4020 | F290: Corporate & Transactional Fees | G290: Revenue | H290: No | I290: 0 | J290: 31447.27 | K290: MIA legal fees billed - 2024-04 | L290: Billing | N290: 2024-04
A291: 290 | B291: 108 | C291: MIA | D291: 2024-04-12 | E291: 4030 | F291: Family Law Fees | G291: Revenue | H291: No | I291: 0 | J291: 23823.7 | K291: MIA legal fees billed - 2024-04 | L291: Billing | N291: 2024-04
A292: 291 | B292: 109 | C292: MIA | D292: 2024-04-24 | E292: 1000 | F292: Cash - Operating | G292: Asset | H292: No | I292: 87675.66 | J292: 0 | K292: MIA client fee collections - 2024-04 | L292: Cash Receipt | N292: 2024-04
A293: 292 | B293: 109 | C293: MIA | D293: 2024-04-24 | E293: 1100 | F293: Accounts Receivable | G293: Asset | H293: No | I293: 0 | J293: 87675.66 | K293: MIA client fee collections - 2024-04 | L293: Cash Receipt | N293: 2024-04
A294: 293 | B294: 110 | C294: MIA | D294: 2024-04-15 | E294: 5010 | F294: Court Filing Fees | G294: COGS | H294: No | I294: 5412.12 | J294: 0 | K294: MIA direct case costs - 2024-04 | L294: AP/Cash | N294: 2024-04
A295: 294 | B295: 110 | C295: MIA | D295: 2024-04-15 | E295: 5020 | F295: Expert Witness Fees | G295: COGS | H295: No | I295: 4428.1 | J295: 0 | K295: MIA direct case costs - 2024-04 | L295: AP/Cash | N295: 2024-04
A296: 295 | B296: 110 | C296: MIA | D296: 2024-04-15 | E296: 1000 | F296: Cash - Operating | G296: Asset | H296: No | I296: 0 | J296: 6888.15 | K296: MIA direct case costs - 2024-04 | L296: AP/Cash | N296: 2024-04
A297: 296 | B297: 110 | C297: MIA | D297: 2024-04-15 | E297: 2000 | F297: Accounts Payable | G297: Liability | H297: No | I297: 0 | J297: 2952.07 | K297: MIA direct case costs - 2024-04 | L297: AP/Cash | N297: 2024-04
A298: 297 | B298: 111 | C298: MIA | D298: 2024-04-29 | E298: 6010 | F298: Attorney & Staff Payroll | G298: Opex | H298: No | I298: 42476 | J298: 0 | K298: MIA payroll run - 2024-04 | L298: Payroll | N298: 2024-04
A299: 298 | B299: 111 | C299: MIA | D299: 2024-04-29 | E299: 6020 | F299: Payroll Taxes & Benefits | G299: Opex | H299: No | I299: 5946.64 | J299: 0 | K299: MIA payroll run - 2024-04 | L299: Payroll | N299: 2024-04
... A371: 370 | B371: 137 | C371: DAL | D371: 2024-04-05 | E371: 1000 | F371: Cash - Operating | G371: Asset | H371: No | I371: 0 | J371: 2190.3 | K371: DAL AP payment run (prior month invoices) - 2024-04 | L371: Cash | N371: 2024-04
A372: 371 | B372: 138 | C372: MIA | D372: 2024-04-22 | E372: 1300 | F372: Intercompany Receivable | G372: Asset | H372: Yes | I372: 3320.72 | J372: 0 | K372: Shared services billed to branch 2 - 2024-04 | L372: Intercompany | M372: CHI | N372: 2024-04
A373: 372 | B373: 138 | C373: MIA | D373: 2024-04-22 | E373: 4090 | F373: Intercompany Shared Services Revenue | G373: Revenue | H373: Yes | I373: 0 | J373: 3320.72 | K373: Shared services billed to branch 2 - 2024-04 | L373: Intercompany | M373: CHI | N373: 2024-04
A374: 373 | B374: 139 | C374: CHI | D374: 2024-04-22 | E374: 6070 | F374: Shared Services Allocation (Intercompany) | G374: Opex | H374: Yes | I374: 3320.72 | J374: 0 | K374: Shared services allocation from HQ - 2024-04 | L374: Intercompany | M374: MIA | N374: 2024-04
A375: 374 | B375: 139 | C375: CHI | D375: 2024-04-22 | E375: 2200 | F375: Intercompany Payable | G375: Liability | H375: Yes | I375: 0 | J375: 3320.72 | K375: Shared services allocation from HQ - 2024-04 | L375: Intercompany | M375: MIA | N375: 2024-04
A376: 375 | B376: 140 | C376: CHI | D376: 2024-04-25 | E376: 2200 | F376: Intercompany Payable | G376: Liability | H376: Yes | I376: 3288.48 | J376: 0 | K376: Intercompany settlement paid to HQ - 2024-04 | L376: Intercompany Cash | M376: MIA | N376: 2024-04
A377: 376 | B377: 140 | C377: CHI | D377: 2024-04-25 | E377: 1000 | F377: Cash - Operating | G377: Asset | H377: No | I377: 0 | J377: 3288.48 | K377: Intercompany settlement paid to HQ - 2024-04 | L377: Intercompany Cash | M377: MIA | N377: 2024-04
A378: 377 | B378: 141 | C378: MIA | D378: 2024-04-25 | E378: 1000 | F378: Cash - Operating | G378: Asset | H378: No | I378: 3288.48 | J378: 0 | K378: Intercompany settlement received from branch 2 - 2024-04 | L378: Intercompany Cash | M378: CHI | N378: 2024-04
A379: 378 | B379: 141 | C379: MIA | D379: 2024-04-25 | E379: 1300 | F379: Intercompany Receivable | G379: Asset | H379: Yes | I379: 0 | J379: 3288.48 | K379: Intercompany settlement received from branch 2 - 2024-04 | L379: Intercompany Cash | M379: CHI | N379: 2024-04
A380: 379 | B380: 142 | C380: MIA | D380: 2024-04-22 | E380: 1300 | F380: Intercompany Receivable | G380: Asset | H380: Yes | I380: 2945.8 | J380: 0 | K380: Shared services billed to branch 3 - 2024-04 | L380: Intercompany | M380: DAL | N380: 2024-04
A381: 380 | B381: 142 | C381: MIA | D381: 2024-04-22 | E381: 4090 | F381: Intercompany Shared Services Revenue | G381: Revenue | H381: Yes | I381: 0 | J381: 2945.8 | K381: Shared services billed to branch 3 - 2024-04 | L381: Intercompany | M381: DAL | N381: 2024-04
A382: 381 | B382: 143 | C382: DAL | D382: 2024-04-22 | E382: 6070 | F382: Shared Services Allocation (Intercompany) | G382: Opex | H382: Yes | I382: 2945.8 | J382: 0 | K382: Shared services allocation from HQ - 2024-04 | L382: Intercompany | M382: MIA | N382: 2024-04
A383: 382 | B383: 143 | C383: DAL | D383: 2024-04-22 | E383: 2200 | F383: Intercompany Payable | G383: Liability | H383: Yes | I383: 0 | J383: 2945.8 | K383: Shared services allocation from HQ - 2024-04 | L383: Intercompany | M383: MIA | N383: 2024-04
... A387: 386 | B387: 145 | C387: MIA | D387: 2024-04-25 | E387: 1300 | F387: Intercompany Receivable | G387: Asset | H387: Yes | I387: 0 | J387: 2917.2 | K387: Intercompany settlement received from branch 3 - 2024-04 | L387: Intercompany Cash | M387: DAL | N387: 2024-04
...

Sheet PQ_Bank_Data
A1: BankTxnID | B1: EntityCode | C1: Date | D1: Amount | E1: Description | F1: Category | G1: MatchedTxnID | H1: MonthKey
A2: 1 | B2: MIA | C2: 2024-01-24 | D2: 89893.86 | E2: MIA client fee collections - 2024-01 | F2: Matched | G2: 5 | H2: 2024-01
A3: 2 | B3: MIA | C3: 2024-01-15 | D3: -6920.48 | E3: MIA direct case costs - 2024-01 | F3: Matched | G3: 9 | H3: 2024-01
A4: 3 | B4: MIA | C4: 2024-01-29 | D4: -42066 | E4: MIA payroll run - 2024-01 | F4: Matched | G4: 13 | H4: 2024-01
A5: 4 | B5: MIA | C5: 2024-01-01 | D5: -6800 | E5: MIA office rent - 2024-01 | F5: Matched | G5: 17 | H5: 2024-01
A6: 5 | B6: MIA | C6: 2024-01-18 | D6: -2664.13 | E6: MIA marketing spend - 2024-01 | F6: Matched | G6: 19 | H6: 2024-01
A7: 6 | B7: MIA | C7: 2024-01-09 | D7: -2100 | E7: MIA software & IT subscriptions - 2024-01 | F7: Matched | G7: 24 | H7: 2024-01
A8: 7 | B8: MIA | C8: 2024-02-26 | D8: 94369 | E8: MIA client fee collections - 2024-02 | F8: Matched | G8: 91 | H8: 2024-02
A9: 8 | B9: MIA | C9: 2024-02-15 | D9: -7284.8 | E9: MIA direct case costs - 2024-02 | F9: Matched | G9: 95 | H9: 2024-02
A10: 9 | B10: MIA | C10: 2024-02-28 | D10: -47244.79 | E10: MIA payroll run - 2024-02 | F10: Matched | G10: 99 | H10: 2024-02
A11: 10 | B11: MIA | C11: 2024-02-01 | D11: -6834 | E11: MIA office rent - 2024-02 | F11: Matched | G11: 103 | H11: 2024-02
A12: 11 | B12: MIA | C12: 2024-02-19 | D12: -2771.12 | E12: MIA marketing spend - 2024-02 | F12: Matched | G12: 105 | H12: 2024-02
A13: 12 | B13: MIA | C13: 2024-02-09 | D13: -2121 | E13: MIA software & IT subscriptions - 2024-02 | F13: Matched | G13: 110 | H13: 2024-02
... A441: 440 | B441: DAL | C441: 2025-06-25 | D441: -3317.6 | E441: Intercompany settlement paid to HQ - 2025-06 | F441: Matched | G441: 1784 | H441: 2025-06
A442: 441 | B442: MIA | C442: 2025-06-30 | D442: -50 | E442: Monthly account service fee | F442: Unmatched - Book Adjustment Needed | H442: 2025-06
A443: 442 | B443: MIA | C443: 2025-06-30 | D443: 40 | E443: Interest income | F443: Unmatched - Book Adjustment Needed | H443: 2025-06
A444: 443 | B444: CHI | C444: 2025-06-30 | D444: -44.3 | E444: Monthly account service fee | F444: Unmatched - Book Adjustment Needed | H444: 2025-06
A445: 444 | B445: CHI | C445: 2025-06-30 | D445: 31.64 | E445: Interest income | F445: Unmatched - Book Adjustment Needed | H445: 2025-06
A446: 445 | B446: DAL | C446: 2025-06-30 | D446: -43.25 | E446: Monthly account service fee | F446: Unmatched - Book Adjustment Needed | H446: 2025-06
A447: 446 | B447: DAL | C447: 2025-06-30 | D447: 30.1 | E447: Interest income | F447: Unmatched - Book Adjustment Needed | H447: 2025-06

Sheet PQ_Budget_Data
A1: BudgetID | B1: EntityCode | C1: Month | D1: AccountCode | E1: AccountName | F1: BudgetAmount | G1: MonthKey
A2: 1 | B2: MIA | C2: 2024-01-01 | D2: 4010 | E2: Litigation Fees | F2: 37497.4 | G2: 2024-01
A3: 2 | B3: MIA | C3: 2024-01-01 | D3: 4020 | E3: Corporate & Transactional Fees | F3: 30252.17 | G3: 2024-01
A4: 3 | B4: MIA | C4: 2024-01-01 | D4: 4030 | E4: Family Law Fees | F4: 22794.28 | G4: 2024-01
A5: 4 | B5: MIA | C5: 2024-01-01 | D5: 6010 | E5: Attorney & Staff Payroll | F5: 41157.23 | G5: 2024-01
A6: 5 | B6: MIA | C6: 2024-01-01 | D6: 6020 | E6: Payroll Taxes & Benefits | F6: 5823.86 | G6: 2024-01
A7: 6 | B7: MIA | C7: 2024-01-01 | D7: 6030 | E7: Office Rent | F7: 6687.65 | G7: 2024-01
A8: 7 | B8: MIA | C8: 2024-01-01 | D8: 6040 | E8: Marketing & Business Development | F8: 3252.16 | G8: 2024-01
A9: 8 | B9: MIA | C9: 2024-01-01 | D9: 6050 | E9: Professional Insurance | F9: 1422.73 | G9: 2024-01
A10: 9 | B10: MIA | C10: 2024-01-01 | D10: 6060 | E10: Software & IT | F10: 2040.91 | G10: 2024-01
A11: 10 | B11: MIA | C11: 2024-01-01 | D11: 7000 | E11: Depreciation Expense | F11: 1100.24 | G11: 2024-01
A12: 11 | B12: CHI | C12: 2024-01-01 | D12: 4010 | E12: Litigation Fees | F12: 20613.41 | G12: 2024-01
A13: 12 | B13: CHI | C13: 2024-01-01 | D13: 4020 | E13: Corporate & Transactional Fees | F13: 16965.32 | G13: 2024-01
... A577: 576 | B577: DAL | C577: 2025-06-01 | D577: 6070 | E577: Shared Services Allocation (Intercompany) | F577: 3346.2 | G577: 2025-06

Sheet PQ_Entity_Dim
A1: EntityID | B1: EntityCode | C1: EntityName | D1: City | E1: EntityType | F1: ParentEntityID | G1: IsGroupHQ
A2: 1 | B2: MIA | C2: P&V Miami (HQ) | D2: Miami, FL | E2: Office | G2: 1
A3: 2 | B3: CHI | C3: P&V Chicago | D3: Chicago, IL | E3: Office | F3: 1 | G3: 0
A4: 3 | B4: DAL | C4: P&V Dallas | D4: Dallas, TX | E4: Office | F4: 1 | G4: 0

Sheet PQ_Account_Dim
A1: AccountID | B1: AccountCode | C1: AccountName | D1: AccountType | E1: ParentAccountID | F1: IsIntercompany | G1: NormalBalance
A2: 1 | B2: 1000 | C2: Cash - Operating | D2: Asset | F2: No | G2: Debit
A3: 2 | B3: 1100 | C3: Accounts Receivable | D3: Asset | F3: No | G3: Debit
A4: 3 | B4: 1200 | C4: Prepaid Expenses | D4: Asset | F4: No | G4: Debit
A5: 4 | B5: 1300 | C5: Intercompany Receivable | D5: Asset | F5: Yes | G5: Debit
A6: 5 | B6: 1500 | C6: Fixed Assets, Net | D6: Asset | F6: No | G6: Debit
A7: 6 | B7: 2000 | C7: Accounts Payable | D7: Liability | F7: No | G7: Credit
A8: 7 | B8: 2100 | C8: Accrued Payroll | D8: Liability | F8: No | G8: Credit
A9: 8 | B9: 2200 | C9: Intercompany Payable | D9: Liability | F9: Yes | G9: Credit
A10: 9 | B10: 3000 | C10: Owner's Equity / Retained Earnings | D10: Equity | F10: No | G10: Credit
A11: 10 | B11: 4000 | C11: Legal Fee Revenue | D11: Revenue | F11: No | G11: Credit
A12: 11 | B12: 4010 | C12: Litigation Fees | D12: Revenue | E12: 10 | F12: No | G12: Credit
A13: 12 | B13: 4020 | C13: Corporate & Transactional Fees | D13: Revenue | E13: 10 | F13: No | G13: Credit
A14: 13 | B14: 4030 | C14: Family Law Fees | D14: Revenue | E14: 10 | F14: No | G14: Credit
A15: 14 | B15: 4090 | C15: Intercompany Shared Services Revenue | D15: Revenue | F15: Yes | G15: Credit
A16: 15 | B16: 5000 | C16: Direct Case Costs | D16: COGS | F16: No | G16: Debit
A17: 16 | B17: 5010 | C17: Court Filing Fees | D17: COGS | E17: 15 | F17: No | G17: Debit
A18: 17 | B18: 5020 | C18: Expert Witness Fees | D18: COGS | E18: 15 | F18: No | G18: Debit
A19: 18 | B19: 6000 | C19: Operating Expenses | D19: Opex | F19: No | G19: Debit
A20: 19 | B20: 6010 | C20: Attorney & Staff Payroll | D20: Opex | E20: 18 | F20: No | G20: Debit
A21: 20 | B21: 6020 | C21: Payroll Taxes & Benefits | D21: Opex | E21: 18 | F21: No | G21: Debit
A22: 21 | B22: 6030 | C22: Office Rent | D22: Opex | E22: 18 | F22: No | G22: Debit
A23: 22 | B23: 6040 | C23: Marketing & Business Development | D23: Opex | E23: 18 | F23: No | G23: Debit
A24: 23 | B24: 6050 | C24: Professional Insurance | D24: Opex | E24: 18 | F24: No | G24: Debit
A25: 24 | B25: 6060 | C25: Software & IT | D25: Opex | E25: 18 | F25: No | G25: Debit
A26: 25 | B26: 6070 | C26: Shared Services Allocation (Intercompany) | D26: Opex | E26: 18 | F26: Yes | G26: Debit
A27: 26 | B27: 7000 | C27: Depreciation Expense | D27: Opex | F27: No | G27: Debit
A28: 27 | B28: 8000 | C28: Interest Expense | D28: Opex | F28: No | G28: Debit
